modules/include_all.sv
`include "modules/defines.sv"
`include "modules/pwm.sv"
`include "modules/edge_det.sv"
`include "modules/sync.sv"

modules/defines.sv
`define reg(val) reg[$clog2(val)-1:0]
`define wire(val) wire[$clog2(val)-1:0]

`define div(A, B) A / B + (2*(A % B) >= B ? 1 : 0)

modules/sync.sv
`include "modules/defines.sv"

module sync #(parameter
							width = 1
						 )
			 (
				 input wire clk,
				 input wire[width-1:0] data_raw,
				 output reg[width-1:0] data = 0
			 );

reg[width-1:0] internal = 0;

always @(posedge clk)
	{ data, internal } <= { internal, data_raw };

endmodule

modules/edge_det.sv
module edge_det
			 (
				 input wire clk,
				 input wire sgn,
				 output wire out_p,
				 output wire out_n,
				 output wire out
			 );

reg sgn_pre = 0;

assign out_p = sgn && ~sgn_pre,
			 out_n = ~sgn && sgn_pre,
			 out = sgn ^ sgn_pre;

always @(posedge clk)
	if (out) sgn_pre <= sgn;

endmodule

entry.sv
`include "modules/include_all.sv"

localparam 	DELAY = 50,
						PERIOD = 20,
						EDGE_CNT_MAX = 3;

typedef enum { STATE_0, STATE_1, STATE_2, STATE_3 } State;

module entry (
				 input wire clk,
				 input wire data_raw,
				 output wire data,
				 output `reg(STATE_3) state = STATE_0,
				 output `reg(DELAY) tmr = DELAY - 1,
				 output wire uart_clk,
				 output wire uart_clk_2
			 );

`reg(EDGE_CNT_MAX) 	edge_cnt = 0;

wire	data_edge,
		 data_edge_p;

wire cond_1 = data_edge_p,
		 cond_2 = data_edge_p && (edge_cnt == EDGE_CNT_MAX - 1),
		 cond_3 = !tmr,
		 cond_0 = !tmr;

//pwm #(.clk_mhz(100), .freq_khz(500), .duty(25)) pwm_ins(.clk(clk), .rst(1'd0), .out(uart_clk));
edge_det edge_det_ins(.clk(clk), .sgn(data), .out_p(data_edge_p), .out(data_edge));
// clock domain crossing double trigger synchronizer: data_raw -> data
sync sync_ins(.clk(clk), .data_raw(data_raw), .data(data));

always @(posedge clk) begin
	// data edge detector
	if (data_edge_p) edge_cnt <= edge_cnt + 1;

	// timer
	case(state)
		STATE_2: tmr <= (!tmr) ? PERIOD - 1 : tmr - 1;
		STATE_3: tmr <= (data_edge || !tmr) ? PERIOD - 1 : tmr - 1;
	endcase

	// FSM
	case(state)
		STATE_0: if (cond_1) state <= STATE_1;
		STATE_1: if (cond_2) state <= STATE_2;
		STATE_2: if (cond_3) state <= STATE_3;
		STATE_3: if (cond_0) state <= STATE_0;
	endcase
end

endmodule

tb.sv
`timescale 1ns/1ps
`include "entry.sv"

module test_entry;

reg clk_tb, data_tb;
wire data_tb_2,
		 uart_clk_tb,
		 uart_clk_tb_2;
wire[1:0]	state_tb;
wire[5:0] tmr_tb;


//устанавливаем экземпляр тестируемого модуля
//entry entry_inst(tclk, data, out, state_value);
entry entry_inst(
				.clk(clk_tb),
				.data_raw(data_tb),
				.data(data_tb_2),
				.state(state_tb),
				.tmr(tmr_tb),
				.uart_clk(uart_clk_tb),
				.uart_clk_2(uart_clk_tb_2)
			);

int i = 0;

//моделируем сигнал тактовой частоты
always #5 clk_tb = ~clk_tb;

//от начала времени...

initial begin
	clk_tb = 0;
	data_tb = 0;
	#100 data_tb = 0;

	for (i = 0; i < 20; i = i + 1)
		#100 data_tb = ~data_tb;
end


//always #100 data_tb = ~data_tb;



//заканчиваем симуляцию в момент времени "400"
initial #5000 $finish;


//создаем файл VCD для последующего анализа сигналов
initial begin
	$dumpfile("out.vcd");
	$dumpvars(0, test_entry);
end


//наблюдаем на некоторыми сигналами системы
initial $monitor(
		$stime,,
		clk_tb,,,
		data_tb,,
		data_tb_2,,
		state_tb,,
		tmr_tb,,
		uart_clk_tb,,
		uart_clk_tb_2
	);

/*
`define s(a) ($clog2(a)+1)'(a)
initial $display(`s(-330));
*/

endmodule

out.vcd
$date
	Sun Mar 22 12:22:38 2020
$end
$version
	Icarus Verilog
$end
$timescale
	1ps
$end
$scope module test_entry $end
$var wire 1 ! uart_clk_tb $end
$var wire 1 " uart_clk_tb_2 $end
$var wire 6 # tmr_tb [5:0] $end
$var wire 2 $ state_tb [1:0] $end
$var wire 1 % data_tb_2 $end
$var reg 1 & clk_tb $end
$var reg 1 ' data_tb $end
$var integer 32 ( i [31:0] $end
$scope module entry_inst $end
$var wire 1 & clk $end
$var wire 1 ) cond_1 $end
$var wire 1 * cond_2 $end
$var wire 1 ' data_raw $end
$var wire 1 ! uart_clk $end
$var wire 1 " uart_clk_2 $end
$var wire 1 + data_edge_p $end
$var wire 1 , data_edge $end
$var wire 1 % data $end
$var wire 1 - cond_3 $end
$var wire 1 . cond_0 $end
$var reg 2 / edge_cnt [1:0] $end
$var reg 2 0 state [1:0] $end
$var reg 6 1 tmr [5:0] $end
$scope module edge_det_ins $end
$var wire 1 & clk $end
$var wire 1 , out $end
$var wire 1 2 out_n $end
$var wire 1 + out_p $end
$var wire 1 % sgn $end
$var reg 1 3 sgn_pre $end
$upscope $end
$scope module sync_ins $end
$var wire 1 & clk $end
$var wire 1 ' data_raw $end
$var reg 1 % data $end
$var reg 1 4 internal $end
$upscope $end
$upscope $end
$upscope $end
$enddefinitions $end
#0
$dumpvars
04
03
02
b110001 1
b0 0
b0 /
0.
0-
0,
0+
0*
0)
b0 (
0'
0&
0%
b0 $
b110001 #
z"
z!
$end
#5000
1&
#10000
0&
#15000
1&
#20000
0&
#25000
1&
#30000
0&
#35000
1&
#40000
0&
#45000
1&
#50000
0&
#55000
1&
#60000
0&
#65000
1&
#70000
0&
#75000
1&
#80000
0&
#85000
1&
#90000
0&
#95000
1&
#100000
0&
#105000
1&
#110000
0&
#115000
1&
#120000
0&
#125000
1&
#130000
0&
#135000
1&
#140000
0&
#145000
1&
#150000
0&
#155000
1&
#160000
0&
#165000
1&
#170000
0&
#175000
1&
#180000
0&
#185000
1&
#190000
0&
#195000
1&
#200000
0&
b1 (
1'
#205000
14
1&
#210000
0&
#215000
1,
1)
1+
1%
1&
#220000
0&
#225000
0)
0+
0,
13
b1 $
b1 0
b1 /
1&
#230000
0&
#235000
1&
#240000
0&
#245000
1&
#250000
0&
#255000
1&
#260000
0&
#265000
1&
#270000
0&
#275000
1&
#280000
0&
#285000
1&
#290000
0&
#295000
1&
#300000
0&
b10 (
0'
#305000
04
1&
#310000
0&
#315000
12
1,
0%
1&
#320000
0&
#325000
0,
02
03
1&
#330000
0&
#335000
1&
#340000
0&
#345000
1&
#350000
0&
#355000
1&
#360000
0&
#365000
1&
#370000
0&
#375000
1&
#380000
0&
#385000
1&
#390000
0&
#395000
1&
#400000
0&
b11 (
1'
#405000
14
1&
#410000
0&
#415000
1,
1)
1+
1%
1&
#420000
0&
#425000
0)
0+
0,
0*
13
b10 /
1&
#430000
0&
#435000
1&
#440000
0&
#445000
1&
#450000
0&
#455000
1&
#460000
0&
#465000
1&
#470000
0&
#475000
1&
#480000
0&
#485000
1&
#490000
0&
#495000
1&
#500000
0&
b100 (
0'
#505000
04
1&
#510000
0&
#515000
12
1,
0%
1&
#520000
0&
#525000
0,
02
03
1&
#530000
0&
#535000
1&
#540000
0&
#545000
1&
#550000
0&
#555000
1&
#560000
0&
#565000
1&
#570000
0&
#575000
1&
#580000
0&
#585000
1&
#590000
0&
#595000
1&
#600000
0&
b101 (
1'
#605000
14
1&
#610000
0&
#615000
1*
1,
1)
1+
1%
1&
#620000
0&
#625000
0)
0+
0,
0*
13
b10 $
b10 0
b11 /
1&
#630000
0&
#635000
b110000 #
b110000 1
1&
#640000
0&
#645000
b101111 #
b101111 1
1&
#650000
0&
#655000
b101110 #
b101110 1
1&
#660000
0&
#665000
b101101 #
b101101 1
1&
#670000
0&
#675000
b101100 #
b101100 1
1&
#680000
0&
#685000
b101011 #
b101011 1
1&
#690000
0&
#695000
b101010 #
b101010 1
1&
#700000
0&
b110 (
0'
#705000
04
b101001 #
b101001 1
1&
#710000
0&
#715000
12
1,
b101000 #
b101000 1
0%
1&
#720000
0&
#725000
0,
02
03
b100111 #
b100111 1
1&
#730000
0&
#735000
b100110 #
b100110 1
1&
#740000
0&
#745000
b100101 #
b100101 1
1&
#750000
0&
#755000
b100100 #
b100100 1
1&
#760000
0&
#765000
b100011 #
b100011 1
1&
#770000
0&
#775000
b100010 #
b100010 1
1&
#780000
0&
#785000
b100001 #
b100001 1
1&
#790000
0&
#795000
b100000 #
b100000 1
1&
#800000
0&
b111 (
1'
#805000
14
b11111 #
b11111 1
1&
#810000
0&
#815000
1,
1)
1+
b11110 #
b11110 1
1%
1&
#820000
0&
#825000
0)
0+
0,
13
b11101 #
b11101 1
b0 /
1&
#830000
0&
#835000
b11100 #
b11100 1
1&
#840000
0&
#845000
b11011 #
b11011 1
1&
#850000
0&
#855000
b11010 #
b11010 1
1&
#860000
0&
#865000
b11001 #
b11001 1
1&
#870000
0&
#875000
b11000 #
b11000 1
1&
#880000
0&
#885000
b10111 #
b10111 1
1&
#890000
0&
#895000
b10110 #
b10110 1
1&
#900000
0&
b1000 (
0'
#905000
04
b10101 #
b10101 1
1&
#910000
0&
#915000
12
1,
b10100 #
b10100 1
0%
1&
#920000
0&
#925000
0,
02
03
b10011 #
b10011 1
1&
#930000
0&
#935000
b10010 #
b10010 1
1&
#940000
0&
#945000
b10001 #
b10001 1
1&
#950000
0&
#955000
b10000 #
b10000 1
1&
#960000
0&
#965000
b1111 #
b1111 1
1&
#970000
0&
#975000
b1110 #
b1110 1
1&
#980000
0&
#985000
b1101 #
b1101 1
1&
#990000
0&
#995000
b1100 #
b1100 1
1&
#1000000
0&
b1001 (
1'
#1005000
14
b1011 #
b1011 1
1&
#1010000
0&
#1015000
1,
1)
1+
b1010 #
b1010 1
1%
1&
#1020000
0&
#1025000
0)
0+
0,
13
b1001 #
b1001 1
b1 /
1&
#1030000
0&
#1035000
b1000 #
b1000 1
1&
#1040000
0&
#1045000
b111 #
b111 1
1&
#1050000
0&
#1055000
b110 #
b110 1
1&
#1060000
0&
#1065000
b101 #
b101 1
1&
#1070000
0&
#1075000
b100 #
b100 1
1&
#1080000
0&
#1085000
b11 #
b11 1
1&
#1090000
0&
#1095000
b10 #
b10 1
1&
#1100000
0&
b1010 (
0'
#1105000
04
b1 #
b1 1
1&
#1110000
0&
#1115000
12
1,
1.
1-
b0 #
b0 1
0%
1&
#1120000
0&
#1125000
0,
02
03
b11 $
b11 0
0.
0-
b10011 #
b10011 1
1&
#1130000
0&
#1135000
b10010 #
b10010 1
1&
#1140000
0&
#1145000
b10001 #
b10001 1
1&
#1150000
0&
#1155000
b10000 #
b10000 1
1&
#1160000
0&
#1165000
b1111 #
b1111 1
1&
#1170000
0&
#1175000
b1110 #
b1110 1
1&
#1180000
0&
#1185000
b1101 #
b1101 1
1&
#1190000
0&
#1195000
b1100 #
b1100 1
1&
#1200000
0&
b1011 (
1'
#1205000
14
b1011 #
b1011 1
1&
#1210000
0&
#1215000
1,
1)
1+
b1010 #
b1010 1
1%
1&
#1220000
0&
#1225000
0)
0+
0,
0*
13
b10011 #
b10011 1
b10 /
1&
#1230000
0&
#1235000
b10010 #
b10010 1
1&
#1240000
0&
#1245000
b10001 #
b10001 1
1&
#1250000
0&
#1255000
b10000 #
b10000 1
1&
#1260000
0&
#1265000
b1111 #
b1111 1
1&
#1270000
0&
#1275000
b1110 #
b1110 1
1&
#1280000
0&
#1285000
b1101 #
b1101 1
1&
#1290000
0&
#1295000
b1100 #
b1100 1
1&
#1300000
0&
b1100 (
0'
#1305000
04
b1011 #
b1011 1
1&
#1310000
0&
#1315000
12
1,
b1010 #
b1010 1
0%
1&
#1320000
0&
#1325000
0,
02
03
b10011 #
b10011 1
1&
#1330000
0&
#1335000
b10010 #
b10010 1
1&
#1340000
0&
#1345000
b10001 #
b10001 1
1&
#1350000
0&
#1355000
b10000 #
b10000 1
1&
#1360000
0&
#1365000
b1111 #
b1111 1
1&
#1370000
0&
#1375000
b1110 #
b1110 1
1&
#1380000
0&
#1385000
b1101 #
b1101 1
1&
#1390000
0&
#1395000
b1100 #
b1100 1
1&
#1400000
0&
b1101 (
1'
#1405000
14
b1011 #
b1011 1
1&
#1410000
0&
#1415000
1*
1,
1)
1+
b1010 #
b1010 1
1%
1&
#1420000
0&
#1425000
0)
0+
0,
0*
13
b10011 #
b10011 1
b11 /
1&
#1430000
0&
#1435000
b10010 #
b10010 1
1&
#1440000
0&
#1445000
b10001 #
b10001 1
1&
#1450000
0&
#1455000
b10000 #
b10000 1
1&
#1460000
0&
#1465000
b1111 #
b1111 1
1&
#1470000
0&
#1475000
b1110 #
b1110 1
1&
#1480000
0&
#1485000
b1101 #
b1101 1
1&
#1490000
0&
#1495000
b1100 #
b1100 1
1&
#1500000
0&
b1110 (
0'
#1505000
04
b1011 #
b1011 1
1&
#1510000
0&
#1515000
12
1,
b1010 #
b1010 1
0%
1&
#1520000
0&
#1525000
0,
02
03
b10011 #
b10011 1
1&
#1530000
0&
#1535000
b10010 #
b10010 1
1&
#1540000
0&
#1545000
b10001 #
b10001 1
1&
#1550000
0&
#1555000
b10000 #
b10000 1
1&
#1560000
0&
#1565000
b1111 #
b1111 1
1&
#1570000
0&
#1575000
b1110 #
b1110 1
1&
#1580000
0&
#1585000
b1101 #
b1101 1
1&
#1590000
0&
#1595000
b1100 #
b1100 1
1&
#1600000
0&
b1111 (
1'
#1605000
14
b1011 #
b1011 1
1&
#1610000
0&
#1615000
1,
1)
1+
b1010 #
b1010 1
1%
1&
#1620000
0&
#1625000
0)
0+
0,
13
b10011 #
b10011 1
b0 /
1&
#1630000
0&
#1635000
b10010 #
b10010 1
1&
#1640000
0&
#1645000
b10001 #
b10001 1
1&
#1650000
0&
#1655000
b10000 #
b10000 1
1&
#1660000
0&
#1665000
b1111 #
b1111 1
1&
#1670000
0&
#1675000
b1110 #
b1110 1
1&
#1680000
0&
#1685000
b1101 #
b1101 1
1&
#1690000
0&
#1695000
b1100 #
b1100 1
1&
#1700000
0&
b10000 (
0'
#1705000
04
b1011 #
b1011 1
1&
#1710000
0&
#1715000
12
1,
b1010 #
b1010 1
0%
1&
#1720000
0&
#1725000
0,
02
03
b10011 #
b10011 1
1&
#1730000
0&
#1735000
b10010 #
b10010 1
1&
#1740000
0&
#1745000
b10001 #
b10001 1
1&
#1750000
0&
#1755000
b10000 #
b10000 1
1&
#1760000
0&
#1765000
b1111 #
b1111 1
1&
#1770000
0&
#1775000
b1110 #
b1110 1
1&
#1780000
0&
#1785000
b1101 #
b1101 1
1&
#1790000
0&
#1795000
b1100 #
b1100 1
1&
#1800000
0&
b10001 (
1'
#1805000
14
b1011 #
b1011 1
1&
#1810000
0&
#1815000
1,
1)
1+
b1010 #
b1010 1
1%
1&
#1820000
0&
#1825000
0)
0+
0,
13
b10011 #
b10011 1
b1 /
1&
#1830000
0&
#1835000
b10010 #
b10010 1
1&
#1840000
0&
#1845000
b10001 #
b10001 1
1&
#1850000
0&
#1855000
b10000 #
b10000 1
1&
#1860000
0&
#1865000
b1111 #
b1111 1
1&
#1870000
0&
#1875000
b1110 #
b1110 1
1&
#1880000
0&
#1885000
b1101 #
b1101 1
1&
#1890000
0&
#1895000
b1100 #
b1100 1
1&
#1900000
0&
b10010 (
0'
#1905000
04
b1011 #
b1011 1
1&
#1910000
0&
#1915000
12
1,
b1010 #
b1010 1
0%
1&
#1920000
0&
#1925000
0,
02
03
b10011 #
b10011 1
1&
#1930000
0&
#1935000
b10010 #
b10010 1
1&
#1940000
0&
#1945000
b10001 #
b10001 1
1&
#1950000
0&
#1955000
b10000 #
b10000 1
1&
#1960000
0&
#1965000
b1111 #
b1111 1
1&
#1970000
0&
#1975000
b1110 #
b1110 1
1&
#1980000
0&
#1985000
b1101 #
b1101 1
1&
#1990000
0&
#1995000
b1100 #
b1100 1
1&
#2000000
0&
b10011 (
1'
#2005000
14
b1011 #
b1011 1
1&
#2010000
0&
#2015000
1,
1)
1+
b1010 #
b1010 1
1%
1&
#2020000
0&
#2025000
0)
0+
0,
0*
13
b10011 #
b10011 1
b10 /
1&
#2030000
0&
#2035000
b10010 #
b10010 1
1&
#2040000
0&
#2045000
b10001 #
b10001 1
1&
#2050000
0&
#2055000
b10000 #
b10000 1
1&
#2060000
0&
#2065000
b1111 #
b1111 1
1&
#2070000
0&
#2075000
b1110 #
b1110 1
1&
#2080000
0&
#2085000
b1101 #
b1101 1
1&
#2090000
0&
#2095000
b1100 #
b1100 1
1&
#2100000
0&
b10100 (
0'
#2105000
04
b1011 #
b1011 1
1&
#2110000
0&
#2115000
12
1,
b1010 #
b1010 1
0%
1&
#2120000
0&
#2125000
0,
02
03
b10011 #
b10011 1
1&
#2130000
0&
#2135000
b10010 #
b10010 1
1&
#2140000
0&
#2145000
b10001 #
b10001 1
1&
#2150000
0&
#2155000
b10000 #
b10000 1
1&
#2160000
0&
#2165000
b1111 #
b1111 1
1&
#2170000
0&
#2175000
b1110 #
b1110 1
1&
#2180000
0&
#2185000
b1101 #
b1101 1
1&
#2190000
0&
#2195000
b1100 #
b1100 1
1&
#2200000
0&
#2205000
b1011 #
b1011 1
1&
#2210000
0&
#2215000
b1010 #
b1010 1
1&
#2220000
0&
#2225000
b1001 #
b1001 1
1&
#2230000
0&
#2235000
b1000 #
b1000 1
1&
#2240000
0&
#2245000
b111 #
b111 1
1&
#2250000
0&
#2255000
b110 #
b110 1
1&
#2260000
0&
#2265000
b101 #
b101 1
1&
#2270000
0&
#2275000
b100 #
b100 1
1&
#2280000
0&
#2285000
b11 #
b11 1
1&
#2290000
0&
#2295000
b10 #
b10 1
1&
#2300000
0&
#2305000
b1 #
b1 1
1&
#2310000
0&
#2315000
1.
1-
b0 #
b0 1
1&
#2320000
0&
#2325000
b0 $
b0 0
0.
0-
b10011 #
b10011 1
1&
