common.sv
`include "./dist/uart.sv"
`include "./dist/gen.sv"
`include "./dist/pred.sv"
`include "./dist/selector.sv"
`include "./dist/interrupter.sv"

/*
real uart frequency is 9600 Hz
assume 960 kHz for faster simulation
*/

localparam 	GEN_CLK_FREQ = 100_000_000,
						TB_CLK_FREQ = 1_000_000_000,
						UART_FREQ = 960_000,

						FRAME_FREQ = 2 * UART_FREQ,
						FRAME = `div(GEN_CLK_FREQ, FRAME_FREQ),
						FRAME_TB = `div(TB_CLK_FREQ, FRAME_FREQ),
						CLK_FRAME_TB = `div(TB_CLK_FREQ, (2 * GEN_CLK_FREQ)),

						CONF_PAR_MAX = 255,
						FRAME_CNT_MAX_1 = 3 * FRAME,
						FRAME_CNT_MAX_2 = 2 * FRAME,
						DATA_BIT_CNT_MAX = 7;

modules/defines.sv
`define reg(val) reg[$clog2(val+1)-1:0]
`define wire(val) wire[$clog2(val+1)-1:0]

`define div(A, B) A / B + (2*(A % B) >= B ? 1 : 0)

dist/sync.sv
`include "./modules/defines.sv"

module sync #(parameter
							WIDTH = 1
						 )
			 (
				 input wire clk,
				 input wire[WIDTH-1:0] data_raw,
				 output reg[WIDTH-1:0] data = 0
			 );

reg[WIDTH-1:0] internal = 0;

always @(posedge clk)
	{ data, internal } <= { internal, data_raw };

endmodule

modules/edge_det.sv
module edge_det
			 (
				 input wire clk,
				 input wire sgn,
				 output wire out_p,
				 output wire out_n,
				 output wire out
			 );

reg sgn_pre = 0;

assign out_p = sgn && ~sgn_pre,
			 out_n = ~sgn && sgn_pre,
			 out = sgn ^ sgn_pre;

always @(posedge clk)
	if (out) sgn_pre <= sgn;

endmodule

src/pwm.sv
`include "./modules/defines.sv"

module pwm #(parameter
						 CLK_MHZ = 50,
						 FREQ_KHZ = 400,
						 DUTY = 40
						)
			 (
				 input wire clk,
				 input wire rst,
				 output wire out
			 );

localparam cnt_max = `div(1000 * CLK_MHZ, FREQ_KHZ),
					 cnt_duty = `div(DUTY * cnt_max, 100);

`reg(cnt_max) cnt = cnt_max - 1;

always @(posedge clk)
	cnt <= (rst || !cnt) ? cnt_max - 1 : cnt - 1;

assign out = cnt < cnt_duty;

endmodule

src/interrupter.sv
`include "./modules/defines.sv"
`include "./modules/pwm.sv"
`include "./modules/edge_det.sv"
`include "./modules/sync.sv"

module interrupter (
				 input wire clk,
				 input wire gen,
				 output wire out
			 );

reg ff = 0;

pwm #(.CLK_MHZ(100),
			.FREQ_KHZ(25),
			.DUTY(50)
		 )
		inter
		(
			.clk(clk),
			.rst(1'b0),
			.out(pwm_wire)
		);

edge_det gen_p(.clk(clk), .sgn(gen), .out_p(gen_edge_p));

sync gen_d(
			 .clk(clk),
			 .data_raw(gen),
			 .data(gen_del)
		 );

always @(posedge clk) if (gen_edge_p) ff <= !pwm_wire;

assign out = ff && gen_del;

endmodule

dist/selector.sv
`include "./modules/defines.sv"
module edge_det_160478825394809386058092837808
			 (
				 input wire clk,
				 input wire sgn,
				 output wire out_p,
				 output wire out_n,
				 output wire out
			 );

reg sgn_pre = 0;

assign out_p = sgn && ~sgn_pre,
			 out_n = ~sgn && sgn_pre,
			 out = sgn ^ sgn_pre;

always @(posedge clk)
	if (out) sgn_pre <= sgn;

endmodule


	module selector #(parameter
										CLK_MHZ = 100,
										PERIODS_TO_SWITCH = 4,
										RESET_TIMEOUT_US = 4
									 )
	(
		input wire clk,
		input wire gen,
		input wire fb,
		output wire out
	);

typedef enum { STATE_0, STATE_1 } State;

localparam TIMEOUT_CNT_MAX = CLK_MHZ * PERIODS_TO_SWITCH;

`reg(TIMEOUT_CNT_MAX) timeout_cnt = TIMEOUT_CNT_MAX - 1;
`reg(PERIODS_TO_SWITCH) per_to_sw_cnt = PERIODS_TO_SWITCH;
`reg(STATE_1) state = STATE_0;

edge_det_160478825394809386058092837808 edge_det_gen(.clk(clk), .sgn(gen), .out_n(gen_edge_n));
edge_det_160478825394809386058092837808 edge_det_fb(.clk(clk), .sgn(fb), .out_n(fb_edge_n));

// state transition conditions
wire cond_1 = !per_to_sw_cnt && fb_edge_n,	// some gen periods passed
		 cond_0 = !timeout_cnt && !gen;	// no signal on fb input

always @(posedge clk) begin
	// state values
	case(state)
		STATE_0: if (gen_edge_n) per_to_sw_cnt <= per_to_sw_cnt ? per_to_sw_cnt - 1 : PERIODS_TO_SWITCH;
		STATE_1: if (!fb) timeout_cnt <= timeout_cnt - 1;
	endcase

	// state transitions
	case(state)
		STATE_0: if (cond_1) state <= STATE_1;
		STATE_1: if (cond_0) begin
				state <= STATE_0;
				timeout_cnt <= TIMEOUT_CNT_MAX - 1;
			end
	endcase
end

assign out = state == STATE_0 ? gen : fb;

endmodule

dist/pred.sv
`include "./modules/defines.sv"

module pred #(parameter
							PRED_PARAMETER = 255
						 )
			 (
				 input wire clk,
				 input wire sgn,
				 input `wire(PRED_PARAMETER) shift,
				 output reg sgn_pre = 0
			 );

`reg(PRED_PARAMETER) cnt;
initial cnt = shift;

always @(posedge clk) begin
	if (sgn ^ sgn_pre) begin
		if (cnt) cnt <= cnt - 1;
		else begin
			cnt <= shift - 1;
			sgn_pre <= sgn;
		end
	end
end

endmodule

src/gen.sv
`include "./modules/defines.sv"

module gen #(parameter
						 CLK_MHZ = 100,
						 FREQ_KHZ_MIN = 100,	// actual range from 200 to 400
						 FREQ_KHZ_MAX = 400,
						 GEN_PARAMETER = 255
						)
			 (
				 input wire clk,
				 input wire en,
				 input `wire(GEN_PARAMETER) inp,
				 output reg out = 0
			 );

localparam CNT_MIN = `div(500 * CLK_MHZ, FREQ_KHZ_MAX),
					 CNT_MAX = `div(500 * CLK_MHZ, FREQ_KHZ_MIN);

`reg(GEN_PARAMETER) gen_param = 0;
`reg(CNT_MAX) cnt = CNT_MIN - 1 + GEN_PARAMETER;

always @(posedge clk) begin
	if (en) gen_param <= inp;

	if (cnt) cnt <= cnt - 1;
	else begin
		cnt <= CNT_MIN - 1 + gen_param;
		out <= ~out;
	end
end

endmodule

entry.sv
`include "common.sv"

// 9600 Hz uart module uses 54 LE


module entry (
				 input wire clk,
				 input wire uart_data,
				 output `wire_2d(sh_reg, CONF_PAR_MAX, CONF_PAR_4),
				 //output wire[7:0] storage,
				 //output wire[1:0] state
				 output wire out,
				 output wire out_pred,
				 output wire sel
			 );

gen gen_ins(
			.clk(clk),
			.en(1'b1),
			.inp(8'd0),
			.out(out)
		);

pred pred_ins(
			 .clk(clk),
			 .sgn(out),
			 .shift(8'd30),
			 .sgn_pre(out_pred_int)
		 );

selector selector_ins(
					 .clk(clk),
					 .gen(out),
					 .fb(out_pred),
					 .out(sel)
				 );

interrupter inter(
							.clk(clk),
							.gen(out_pred_int),
							.out(out_pred)
						);

/*
uart #(
			 .CONF_PAR_MAX(CONF_PAR_MAX),
			 .FRAME_CNT_MAX_1(FRAME_CNT_MAX_1),
			 .FRAME_CNT_MAX_2(FRAME_CNT_MAX_2),
			 .DATA_BIT_CNT_MAX(DATA_BIT_CNT_MAX)
		 ) uart_ins(
			 .clk(clk),
			 .uart_data(uart_data),
			 .sh_reg(sh_reg)
			 //.storage(storage),
			 //.state(state)
		 );
*/

endmodule

tb.sv
`timescale 1ns/1ns
`include "entry.sv"

module test_entry;

reg clk_tb, uart_data_tb, uart_clk_tb;
wire is_data_ready_tb, out_tb;
`wire_2d(sh_reg_tb, CONF_PAR_MAX, CONF_PAR_4);
`wire(CONF_PAR_MAX) sh_0, sh_1, sh_2, sh_3, sh_4;
//wire[7:0] storage_tb;
//wire[1:0] state_tb;
wire out_pred_tb;
wire sel_tb;

assign sh_0 = sh_reg_tb[0],
			 sh_1 = sh_reg_tb[1],
			 sh_2 = sh_reg_tb[2],
			 sh_3 = sh_reg_tb[3],
			 sh_4 = sh_reg_tb[4];


entry entry_inst(
				.clk(clk_tb),
				.uart_data(uart_data_tb),
				.sh_reg(sh_reg_tb),
				//.storage(storage_tb),
				//.state(state_tb)
				.out(out_tb),
				.out_pred(out_pred_tb),
				.sel(sel_tb)
			);

localparam //test_data = 49'b0_00101100_10_01001100_10_00101100_10_01001100_10_00101100, // 42424
					 test_data = 69'b0_11101100_10_01001100_10_00101100_10_01001100_10_00101100_10_00101100_10_10101100, // 72424_45
					 packet_size = $bits(test_data);

// clk
always #CLK_FRAME_TB clk_tb = ~clk_tb;
always #FRAME_TB uart_clk_tb = ~uart_clk_tb;

initial #(2 * (packet_size + 2) * FRAME_TB) $finish;

initial begin
	clk_tb = 0;
	uart_data_tb = 1;
	uart_clk_tb = 0;

	for (int i = packet_size; i > 0; i--) begin
		#(2 * FRAME_TB) uart_data_tb = test_data[i-1];
		if (i == 1) #(2 * FRAME_TB) uart_data_tb = 1;
	end
end

// creating VCD file for signal analysis
initial begin
	$dumpfile("out.vcd");
	$dumpvars(0, test_entry);
end

// displaying meaning signals
initial $monitor(
		$stime,,
		clk_tb,,
		uart_clk_tb,,
		uart_data_tb,,
		sh_0,,
		sh_1,,
		sh_2,,
		sh_3,,
		sh_4,,
		out_tb,,
		//storage_tb,,
		//state_tb
		out_pred_tb,,
		sel_tb,,
	);

endmodule

out.vcd
$date
	Sun Nov 08 01:30:56 2020
$end
$version
	Icarus Verilog
$end
$timescale
	1ns
$end
$scope module test_entry $end
$var wire 8 ! sh_0 [7:0] $end
$var wire 8 " sh_1 [7:0] $end
$var wire 8 # sh_2 [7:0] $end
$var wire 8 $ sh_3 [7:0] $end
$var wire 8 % sh_4 [7:0] $end
$var wire 1 & sel_tb $end
$var wire 1 ' out_tb $end
$var wire 1 ( out_pred_tb $end
$var reg 1 ) clk_tb $end
$var reg 1 * uart_clk_tb $end
$var reg 1 + uart_data_tb $end
$scope module entry_inst $end
$var wire 1 ) clk $end
$var wire 1 + uart_data $end
$var wire 1 & sel $end
$var wire 1 , out_pred_int $end
$var wire 1 ( out_pred $end
$var wire 1 ' out $end
$scope module gen_ins $end
$var wire 1 ) clk $end
$var wire 1 - en $end
$var wire 8 . inp [7:0] $end
$var reg 9 / cnt [8:0] $end
$var reg 8 0 gen_param [7:0] $end
$var reg 1 ' out $end
$upscope $end
$scope module inter $end
$var wire 1 ) clk $end
$var wire 1 ( out $end
$var wire 1 1 pwm_wire $end
$var wire 1 2 gen_edge_p $end
$var wire 1 3 gen_del $end
$var wire 1 , gen $end
$var reg 1 4 ff $end
$scope module gen_d $end
$var wire 1 ) clk $end
$var wire 1 , data_raw $end
$var reg 1 3 data $end
$var reg 1 5 internal $end
$upscope $end
$scope module gen_p $end
$var wire 1 ) clk $end
$var wire 1 6 out $end
$var wire 1 7 out_n $end
$var wire 1 2 out_p $end
$var wire 1 , sgn $end
$var reg 1 8 sgn_pre $end
$upscope $end
$scope module inter $end
$var wire 1 ) clk $end
$var wire 1 9 rst $end
$var wire 1 1 out $end
$var reg 12 : cnt [11:0] $end
$upscope $end
$upscope $end
$scope module pred_ins $end
$var wire 1 ) clk $end
$var wire 1 ' sgn $end
$var wire 8 ; shift [7:0] $end
$var reg 8 < cnt [7:0] $end
$var reg 1 , sgn_pre $end
$upscope $end
$scope module selector_ins $end
$var wire 1 ) clk $end
$var wire 1 = cond_0 $end
$var wire 1 > cond_1 $end
$var wire 1 ( fb $end
$var wire 1 ' gen $end
$var wire 1 & out $end
$var wire 1 ? gen_edge_n $end
$var wire 1 @ fb_edge_n $end
$var reg 3 A per_to_sw_cnt [2:0] $end
$var reg 1 B state $end
$var reg 9 C timeout_cnt [8:0] $end
$scope module edge_det_fb $end
$var wire 1 ) clk $end
$var wire 1 D out $end
$var wire 1 @ out_n $end
$var wire 1 E out_p $end
$var wire 1 ( sgn $end
$var reg 1 F sgn_pre $end
$upscope $end
$scope module edge_det_gen $end
$var wire 1 ) clk $end
$var wire 1 G out $end
$var wire 1 ? out_n $end
$var wire 1 H out_p $end
$var wire 1 ' sgn $end
$var reg 1 I sgn_pre $end
$upscope $end
$upscope $end
$upscope $end
$scope begin $ivl_for_loop1 $end
$var integer 32 J i [31:0] $end
$upscope $end
$upscope $end
$enddefinitions $end
#0
$dumpvars
b1000101 J
0I
0H
0G
0F
0E
0D
b110001111 C
0B
b100 A
0@
0?
0>
0=
b11110 <
b11110 ;
b111110011111 :
09
08
07
06
05
04
03
02
01
b0 0
b101111011 /
b0 .
1-
0,
1+
0*
0)
0(
0'
0&
bz %
bz $
bz #
bz "
bz !
$end
#5
b101111010 /
b111110011110 :
1)
#10
0)
#15
b111110011101 :
b101111001 /
1)
#20
0)
#25
b101111000 /
b111110011100 :
1)
#30
0)
#35
b111110011011 :
b101110111 /
1)
#40
0)
#45
b101110110 /
b111110011010 :
1)
#50
0)
#55
b111110011001 :
b101110101 /
1)
#60
0)
#65
b101110100 /
b111110011000 :
1)
#70
0)
#75
b111110010111 :
b101110011 /
1)
#80
0)
#85
b101110010 /
b111110010110 :
1)
#90
0)
#95
b111110010101 :
b101110001 /
1)
#100
0)
#105
b101110000 /
b111110010100 :
1)
#110
0)
#115
b111110010011 :
b101101111 /
1)
#120
0)
#125
b101101110 /
b111110010010 :
1)
#130
0)
#135
b111110010001 :
b101101101 /
1)
#140
0)
#145
b101101100 /
b111110010000 :
1)
#150
0)
#155
b111110001111 :
b101101011 /
1)
#160
0)
#165
b101101010 /
b111110001110 :
1)
#170
0)
#175
b111110001101 :
b101101001 /
1)
#180
0)
#185
b101101000 /
b111110001100 :
1)
#190
0)
#195
b111110001011 :
b101100111 /
1)
#200
0)
#205
b101100110 /
b111110001010 :
1)
#210
0)
#215
b111110001001 :
b101100101 /
1)
#220
0)
#225
b101100100 /
b111110001000 :
1)
#230
0)
#235
b111110000111 :
b101100011 /
1)
#240
0)
#245
b101100010 /
b111110000110 :
1)
#250
0)
#255
b111110000101 :
b101100001 /
1)
#260
0)
#265
b101100000 /
b111110000100 :
1)
#270
0)
#275
b111110000011 :
b101011111 /
1)
#280
0)
#285
b101011110 /
b111110000010 :
1)
#290
0)
#295
b111110000001 :
b101011101 /
1)
#300
0)
#305
b101011100 /
b111110000000 :
1)
#310
0)
#315
b111101111111 :
b101011011 /
1)
#320
0)
#325
b101011010 /
b111101111110 :
1)
#330
0)
#335
b111101111101 :
b101011001 /
1)
#340
0)
#345
b101011000 /
b111101111100 :
1)
#350
0)
#355
b111101111011 :
b101010111 /
1)
#360
0)
#365
b101010110 /
b111101111010 :
1)
#370
0)
#375
b111101111001 :
b101010101 /
1)
#380
0)
#385
b101010100 /
b111101111000 :
1)
#390
0)
#395
b111101110111 :
b101010011 /
1)
#400
0)
#405
b101010010 /
b111101110110 :
1)
#410
0)
#415
b111101110101 :
b101010001 /
1)
#420
0)
#425
b101010000 /
b111101110100 :
1)
#430
0)
#435
b111101110011 :
b101001111 /
1)
#440
0)
#445
b101001110 /
b111101110010 :
1)
#450
0)
#455
b111101110001 :
b101001101 /
1)
#460
0)
#465
b101001100 /
b111101110000 :
1)
#470
0)
#475
b111101101111 :
b101001011 /
1)
#480
0)
#485
b101001010 /
b111101101110 :
1)
#490
0)
#495
b111101101101 :
b101001001 /
1)
#500
0)
#505
b101001000 /
b111101101100 :
1)
#510
0)
#515
b111101101011 :
b101000111 /
1)
#520
0)
#521
1*
#525
b101000110 /
b111101101010 :
1)
#530
0)
#535
b111101101001 :
b101000101 /
1)
#540
0)
#545
b101000100 /
b111101101000 :
1)
#550
0)
#555
b111101100111 :
b101000011 /
1)
#560
0)
#565
b101000010 /
b111101100110 :
1)
#570
0)
#575
b111101100101 :
b101000001 /
1)
#580
0)
#585
b101000000 /
b111101100100 :
1)
#590
0)
#595
b111101100011 :
b100111111 /
1)
#600
0)
#605
b100111110 /
b111101100010 :
1)
#610
0)
#615
b111101100001 :
b100111101 /
1)
#620
0)
#625
b100111100 /
b111101100000 :
1)
#630
0)
#635
b111101011111 :
b100111011 /
1)
#640
0)
#645
b100111010 /
b111101011110 :
1)
#650
0)
#655
b111101011101 :
b100111001 /
1)
#660
0)
#665
b100111000 /
b111101011100 :
1)
#670
0)
#675
b111101011011 :
b100110111 /
1)
#680
0)
#685
b100110110 /
b111101011010 :
1)
#690
0)
#695
b111101011001 :
b100110101 /
1)
#700
0)
#705
b100110100 /
b111101011000 :
1)
#710
0)
#715
b111101010111 :
b100110011 /
1)
#720
0)
#725
b100110010 /
b111101010110 :
1)
#730
0)
#735
b111101010101 :
b100110001 /
1)
#740
0)
#745
b100110000 /
b111101010100 :
1)
#750
0)
#755
b111101010011 :
b100101111 /
1)
#760
0)
#765
b100101110 /
b111101010010 :
1)
#770
0)
#775
b111101010001 :
b100101101 /
1)
#780
0)
#785
b100101100 /
b111101010000 :
1)
#790
0)
#795
b111101001111 :
b100101011 /
1)
#800
0)
#805
b100101010 /
b111101001110 :
1)
#810
0)
#815
b111101001101 :
b100101001 /
1)
#820
0)
#825
b100101000 /
b111101001100 :
1)
#830
0)
#835
b111101001011 :
b100100111 /
1)
#840
0)
#845
b100100110 /
b111101001010 :
1)
#850
0)
#855
b111101001001 :
b100100101 /
1)
#860
0)
#865
b100100100 /
b111101001000 :
1)
#870
0)
#875
b111101000111 :
b100100011 /
1)
#880
0)
#885
b100100010 /
b111101000110 :
1)
#890
0)
#895
b111101000101 :
b100100001 /
1)
#900
0)
#905
b100100000 /
b111101000100 :
1)
#910
0)
#915
b111101000011 :
b100011111 /
1)
#920
0)
#925
b100011110 /
b111101000010 :
1)
#930
0)
#935
b111101000001 :
b100011101 /
1)
#940
0)
#945
b100011100 /
b111101000000 :
1)
#950
0)
#955
b111100111111 :
b100011011 /
1)
#960
0)
#965
b100011010 /
b111100111110 :
1)
#970
0)
#975
b111100111101 :
b100011001 /
1)
#980
0)
#985
b100011000 /
b111100111100 :
1)
#990
0)
#995
b111100111011 :
b100010111 /
1)
#1000
0)
#1005
b100010110 /
b111100111010 :
1)
#1010
0)
#1015
b111100111001 :
b100010101 /
1)
#1020
0)
#1025
b100010100 /
b111100111000 :
1)
#1030
0)
#1035
b111100110111 :
b100010011 /
1)
#1040
0)
#1042
0*
b1000100 J
0+
#1045
b100010010 /
b111100110110 :
1)
#1050
0)
#1055
b111100110101 :
b100010001 /
1)
#1060
0)
#1065
b100010000 /
b111100110100 :
1)
#1070
0)
#1075
b111100110011 :
b100001111 /
1)
#1080
0)
#1085
b100001110 /
b111100110010 :
1)
#1090
0)
#1095
b111100110001 :
b100001101 /
1)
#1100
0)
#1105
b100001100 /
b111100110000 :
1)
#1110
0)
#1115
b111100101111 :
b100001011 /
1)
#1120
0)
#1125
b100001010 /
b111100101110 :
1)
#1130
0)
#1135
b111100101101 :
b100001001 /
1)
#1140
0)
#1145
b100001000 /
b111100101100 :
1)
#1150
0)
#1155
b111100101011 :
b100000111 /
1)
#1160
0)
#1165
b100000110 /
b111100101010 :
1)
#1170
0)
#1175
b111100101001 :
b100000101 /
1)
#1180
0)
#1185
b100000100 /
b111100101000 :
1)
#1190
0)
#1195
b111100100111 :
b100000011 /
1)
#1200
0)
#1205
b100000010 /
b111100100110 :
1)
#1210
0)
#1215
b111100100101 :
b100000001 /
1)
#1220
0)
#1225
b100000000 /
b111100100100 :
1)
#1230
0)
#1235
b111100100011 :
b11111111 /
1)
#1240
0)
#1245
b11111110 /
b111100100010 :
1)
#1250
0)
#1255
b111100100001 :
b11111101 /
1)
#1260
0)
#1265
b11111100 /
b111100100000 :
1)
#1270
0)
#1275
b111100011111 :
b11111011 /
1)
#1280
0)
#1285
b11111010 /
b111100011110 :
1)
#1290
0)
#1295
b111100011101 :
b11111001 /
1)
#1300
0)
#1305
b11111000 /
b111100011100 :
1)
#1310
0)
#1315
b111100011011 :
b11110111 /
1)
#1320
0)
#1325
b11110110 /
b111100011010 :
1)
#1330
0)
#1335
b111100011001 :
b11110101 /
1)
#1340
0)
#1345
b11110100 /
b111100011000 :
1)
#1350
0)
#1355
b111100010111 :
b11110011 /
1)
#1360
0)
#1365
b11110010 /
b111100010110 :
1)
#1370
0)
#1375
b111100010101 :
b11110001 /
1)
#1380
0)
#1385
b11110000 /
b111100010100 :
1)
#1390
0)
#1395
b111100010011 :
b11101111 /
1)
#1400
0)
#1405
b11101110 /
b111100010010 :
1)
#1410
0)
#1415
b111100010001 :
b11101101 /
1)
#1420
0)
#1425
b11101100 /
b111100010000 :
1)
#1430
0)
#1435
b111100001111 :
b11101011 /
1)
#1440
0)
#1445
b11101010 /
b111100001110 :
1)
#1450
0)
#1455
b111100001101 :
b11101001 /
1)
#1460
0)
#1465
b11101000 /
b111100001100 :
1)
#1470
0)
#1475
b111100001011 :
b11100111 /
1)
#1480
0)
#1485
b11100110 /
b111100001010 :
1)
#1490
0)
#1495
b111100001001 :
b11100101 /
1)
#1500
0)
#1505
b11100100 /
b111100001000 :
1)
#1510
0)
#1515
b111100000111 :
b11100011 /
1)
#1520
0)
#1525
b11100010 /
b111100000110 :
1)
#1530
0)
#1535
b111100000101 :
b11100001 /
1)
#1540
0)
#1545
b11100000 /
b111100000100 :
1)
#1550
0)
#1555
b111100000011 :
b11011111 /
1)
#1560
0)
#1563
1*
#1565
b11011110 /
b111100000010 :
1)
#1570
0)
#1575
b111100000001 :
b11011101 /
1)
#1580
0)
#1585
b11011100 /
b111100000000 :
1)
#1590
0)
#1595
b111011111111 :
b11011011 /
1)
#1600
0)
#1605
b11011010 /
b111011111110 :
1)
#1610
0)
#1615
b111011111101 :
b11011001 /
1)
#1620
0)
#1625
b11011000 /
b111011111100 :
1)
#1630
0)
#1635
b111011111011 :
b11010111 /
1)
#1640
0)
#1645
b11010110 /
b111011111010 :
1)
#1650
0)
#1655
b111011111001 :
b11010101 /
1)
#1660
0)
#1665
b11010100 /
b111011111000 :
1)
#1670
0)
#1675
b111011110111 :
b11010011 /
1)
#1680
0)
#1685
b11010010 /
b111011110110 :
1)
#1690
0)
#1695
b111011110101 :
b11010001 /
1)
#1700
0)
#1705
b11010000 /
b111011110100 :
1)
#1710
0)
#1715
b111011110011 :
b11001111 /
1)
#1720
0)
#1725
b11001110 /
b111011110010 :
1)
#1730
0)
#1735
b111011110001 :
b11001101 /
1)
#1740
0)
#1745
b11001100 /
b111011110000 :
1)
#1750
0)
#1755
b111011101111 :
b11001011 /
1)
#1760
0)
#1765
b11001010 /
b111011101110 :
1)
#1770
0)
#1775
b111011101101 :
b11001001 /
1)
#1780
0)
#1785
b11001000 /
b111011101100 :
1)
#1790
0)
#1795
b111011101011 :
b11000111 /
1)
#1800
0)
#1805
b11000110 /
b111011101010 :
1)
#1810
0)
#1815
b111011101001 :
b11000101 /
1)
#1820
0)
#1825
b11000100 /
b111011101000 :
1)
#1830
0)
#1835
b111011100111 :
b11000011 /
1)
#1840
0)
#1845
b11000010 /
b111011100110 :
1)
#1850
0)
#1855
b111011100101 :
b11000001 /
1)
#1860
0)
#1865
b11000000 /
b111011100100 :
1)
#1870
0)
#1875
b111011100011 :
b10111111 /
1)
#1880
0)
#1885
b10111110 /
b111011100010 :
1)
#1890
0)
#1895
b111011100001 :
b10111101 /
1)
#1900
0)
#1905
b10111100 /
b111011100000 :
1)
#1910
0)
#1915
b111011011111 :
b10111011 /
1)
#1920
0)
#1925
b10111010 /
b111011011110 :
1)
#1930
0)
#1935
b111011011101 :
b10111001 /
1)
#1940
0)
#1945
b10111000 /
b111011011100 :
1)
#1950
0)
#1955
b111011011011 :
b10110111 /
1)
#1960
0)
#1965
b10110110 /
b111011011010 :
1)
#1970
0)
#1975
b111011011001 :
b10110101 /
1)
#1980
0)
#1985
b10110100 /
b111011011000 :
1)
#1990
0)
#1995
b111011010111 :
b10110011 /
1)
#2000
0)
#2005
b10110010 /
b111011010110 :
1)
#2010
0)
#2015
b111011010101 :
b10110001 /
1)
#2020
0)
#2025
b10110000 /
b111011010100 :
1)
#2030
0)
#2035
b111011010011 :
b10101111 /
1)
#2040
0)
#2045
b10101110 /
b111011010010 :
1)
#2050
0)
#2055
b111011010001 :
b10101101 /
1)
#2060
0)
#2065
b10101100 /
b111011010000 :
1)
#2070
0)
#2075
b111011001111 :
b10101011 /
1)
#2080
0)
#2084
0*
b1000011 J
1+
#2085
b10101010 /
b111011001110 :
1)
#2090
0)
#2095
b111011001101 :
b10101001 /
1)
#2100
0)
#2105
b10101000 /
b111011001100 :
1)
#2110
0)
#2115
b111011001011 :
b10100111 /
1)
#2120
0)
#2125
b10100110 /
b111011001010 :
1)
#2130
0)
#2135
b111011001001 :
b10100101 /
1)
#2140
0)
#2145
b10100100 /
b111011001000 :
1)
#2150
0)
#2155
b111011000111 :
b10100011 /
1)
#2160
0)
#2165
b10100010 /
b111011000110 :
1)
#2170
0)
#2175
b111011000101 :
b10100001 /
1)
#2180
0)
#2185
b10100000 /
b111011000100 :
1)
#2190
0)
#2195
b111011000011 :
b10011111 /
1)
#2200
0)
#2205
b10011110 /
b111011000010 :
1)
#2210
0)
#2215
b111011000001 :
b10011101 /
1)
#2220
0)
#2225
b10011100 /
b111011000000 :
1)
#2230
0)
#2235
b111010111111 :
b10011011 /
1)
#2240
0)
#2245
b10011010 /
b111010111110 :
1)
#2250
0)
#2255
b111010111101 :
b10011001 /
1)
#2260
0)
#2265
b10011000 /
b111010111100 :
1)
#2270
0)
#2275
b111010111011 :
b10010111 /
1)
#2280
0)
#2285
b10010110 /
b111010111010 :
1)
#2290
0)
#2295
b111010111001 :
b10010101 /
1)
#2300
0)
#2305
b10010100 /
b111010111000 :
1)
#2310
0)
#2315
b111010110111 :
b10010011 /
1)
#2320
0)
#2325
b10010010 /
b111010110110 :
1)
#2330
0)
#2335
b111010110101 :
b10010001 /
1)
#2340
0)
#2345
b10010000 /
b111010110100 :
1)
#2350
0)
#2355
b111010110011 :
b10001111 /
1)
#2360
0)
#2365
b10001110 /
b111010110010 :
1)
#2370
0)
#2375
b111010110001 :
b10001101 /
1)
#2380
0)
#2385
b10001100 /
b111010110000 :
1)
#2390
0)
#2395
b111010101111 :
b10001011 /
1)
#2400
0)
#2405
b10001010 /
b111010101110 :
1)
#2410
0)
#2415
b111010101101 :
b10001001 /
1)
#2420
0)
#2425
b10001000 /
b111010101100 :
1)
#2430
0)
#2435
b111010101011 :
b10000111 /
1)
#2440
0)
#2445
b10000110 /
b111010101010 :
1)
#2450
0)
#2455
b111010101001 :
b10000101 /
1)
#2460
0)
#2465
b10000100 /
b111010101000 :
1)
#2470
0)
#2475
b111010100111 :
b10000011 /
1)
#2480
0)
#2485
b10000010 /
b111010100110 :
1)
#2490
0)
#2495
b111010100101 :
b10000001 /
1)
#2500
0)
#2505
b10000000 /
b111010100100 :
1)
#2510
0)
#2515
b111010100011 :
b1111111 /
1)
#2520
0)
#2525
b1111110 /
b111010100010 :
1)
#2530
0)
#2535
b111010100001 :
b1111101 /
1)
#2540
0)
#2545
b1111100 /
b111010100000 :
1)
#2550
0)
#2555
b111010011111 :
b1111011 /
1)
#2560
0)
#2565
b1111010 /
b111010011110 :
1)
#2570
0)
#2575
b111010011101 :
b1111001 /
1)
#2580
0)
#2585
b1111000 /
b111010011100 :
1)
#2590
0)
#2595
b111010011011 :
b1110111 /
1)
#2600
0)
#2605
b1110110 /
b111010011010 :
1)
1*
#2610
0)
#2615
b111010011001 :
b1110101 /
1)
#2620
0)
#2625
b1110100 /
b111010011000 :
1)
#2630
0)
#2635
b111010010111 :
b1110011 /
1)
#2640
0)
#2645
b1110010 /
b111010010110 :
1)
#2650
0)
#2655
b111010010101 :
b1110001 /
1)
#2660
0)
#2665
b1110000 /
b111010010100 :
1)
#2670
0)
#2675
b111010010011 :
b1101111 /
1)
#2680
0)
#2685
b1101110 /
b111010010010 :
1)
#2690
0)
#2695
b111010010001 :
b1101101 /
1)
#2700
0)
#2705
b1101100 /
b111010010000 :
1)
#2710
0)
#2715
b111010001111 :
b1101011 /
1)
#2720
0)
#2725
b1101010 /
b111010001110 :
1)
#2730
0)
#2735
b111010001101 :
b1101001 /
1)
#2740
0)
#2745
b1101000 /
b111010001100 :
1)
#2750
0)
#2755
b111010001011 :
b1100111 /
1)
#2760
0)
#2765
b1100110 /
b111010001010 :
1)
#2770
0)
#2775
b111010001001 :
b1100101 /
1)
#2780
0)
#2785
b1100100 /
b111010001000 :
1)
#2790
0)
#2795
b111010000111 :
b1100011 /
1)
#2800
0)
#2805
b1100010 /
b111010000110 :
1)
#2810
0)
#2815
b111010000101 :
b1100001 /
1)
#2820
0)
#2825
b1100000 /
b111010000100 :
1)
#2830
0)
#2835
b111010000011 :
b1011111 /
1)
#2840
0)
#2845
b1011110 /
b111010000010 :
1)
#2850
0)
#2855
b111010000001 :
b1011101 /
1)
#2860
0)
#2865
b1011100 /
b111010000000 :
1)
#2870
0)
#2875
b111001111111 :
b1011011 /
1)
#2880
0)
#2885
b1011010 /
b111001111110 :
1)
#2890
0)
#2895
b111001111101 :
b1011001 /
1)
#2900
0)
#2905
b1011000 /
b111001111100 :
1)
#2910
0)
#2915
b111001111011 :
b1010111 /
1)
#2920
0)
#2925
b1010110 /
b111001111010 :
1)
#2930
0)
#2935
b111001111001 :
b1010101 /
1)
#2940
0)
#2945
b1010100 /
b111001111000 :
1)
#2950
0)
#2955
b111001110111 :
b1010011 /
1)
#2960
0)
#2965
b1010010 /
b111001110110 :
1)
#2970
0)
#2975
b111001110101 :
b1010001 /
1)
#2980
0)
#2985
b1010000 /
b111001110100 :
1)
#2990
0)
#2995
b111001110011 :
b1001111 /
1)
#3000
0)
#3005
b1001110 /
b111001110010 :
1)
#3010
0)
#3015
b111001110001 :
b1001101 /
1)
#3020
0)
#3025
b1001100 /
b111001110000 :
1)
#3030
0)
#3035
b111001101111 :
b1001011 /
1)
#3040
0)
#3045
b1001010 /
b111001101110 :
1)
#3050
0)
#3055
b111001101101 :
b1001001 /
1)
#3060
0)
#3065
b1001000 /
b111001101100 :
1)
#3070
0)
#3075
b111001101011 :
b1000111 /
1)
