common.sv
`include "./dist/uart.sv"
`include "./dist/ref_gen.sv"
`include "./dist/pred.sv"
`include "./dist/selector.sv"
`include "./dist/interrupter.sv"
`include "./dist/ocd_lvl.sv"

/*
real uart frequency is 9600 Hz
assume 960 kHz for faster simulation
*/

localparam 	GEN_CLK_FREQ = 100_000_000,
						TB_CLK_FREQ = 1_000_000_000,
						UART_FREQ = 320_000,

						FRAME_FREQ = 2 * UART_FREQ,
						FRAME = `div(GEN_CLK_FREQ, FRAME_FREQ),
						FRAME_TB = `div(TB_CLK_FREQ, FRAME_FREQ),
						CLK_FRAME_TB = `div(TB_CLK_FREQ, (2 * GEN_CLK_FREQ)),

						CONF_PAR_MAX = 255,
						FRAME_CNT_MAX_1 = 3 * FRAME,
						FRAME_CNT_MAX_2 = 2 * FRAME,
						DATA_BIT_CNT_MAX = 7;

modules/defines.sv
`define reg(val) reg[$clog2(val+1)-1:0]
`define wire(val) wire[$clog2(val+1)-1:0]

`define div(A, B) A / B + (2*(A % B) >= B ? 1 : 0)

dist/ocd_lvl.sv
`include "./modules/defines.sv"

module ocd_lvl #(parameter
								 CLK_MHZ = 100,
								 FREQ_KHZ = 100,
								 PAR_MAX_VAL = 100
								)
			 (
				 input wire clk,
				 input `wire(PAR_MAX_VAL) pw_par,
				 output wire out
			 );

localparam cnt_max = `div(1000 * CLK_MHZ, FREQ_KHZ),
					 k = `div(cnt_max, PAR_MAX_VAL);

`reg(cnt_max) cnt = cnt_max - 1;

always @(posedge clk)
	cnt <= !cnt ? cnt_max - 1 : cnt - 1;

assign out = cnt < k * pw_par;

endmodule

dist/sync.sv
`include "./modules/defines.sv"

module sync #(parameter
							WIDTH = 1
						 )
			 (
				 input wire clk,
				 input wire[WIDTH-1:0] data_raw,
				 output reg[WIDTH-1:0] data = 0
			 );

reg[WIDTH-1:0] internal = 0;

always @(posedge clk)
	{ data, internal } <= { internal, data_raw };

endmodule

modules/edge_det.sv
module edge_det
			 (
				 input wire clk,
				 input wire sgn,
				 output wire out_p,
				 output wire out_n,
				 output wire out
			 );

reg sgn_pre = 0;

assign out_p = sgn && ~sgn_pre,
			 out_n = ~sgn && sgn_pre,
			 out = sgn ^ sgn_pre;

always @(posedge clk)
	if (out) sgn_pre <= sgn;

endmodule

modules/int_gen.sv
`include "./modules/defines.sv"

module int_gen #(parameter
								 CLK_MHZ = 100,
								 PAR_MAX_VAL = 255
								)
			 (
				 input wire clk,
				 input `wire(PAR_MAX_VAL) freq_par,
				 input `wire(PAR_MAX_VAL) pw_par,
				 output wire out
			 );

localparam k = 100;	// for pw_par in microseconds

`reg(100 * CLK_MHZ) cnt = 0; // 500_000

always @(posedge clk) begin
	if (cnt) cnt <= cnt - 1;
	else begin
		case(freq_par)
			`lookup
		endcase
	end
end

assign out = cnt < k * pw_par;

endmodule

src/interrupter.sv
`include "./modules/defines.sv"
`include "./modules/int_gen.sv"
`include "./modules/edge_det.sv"
`include "./modules/sync.sv"

module interrupter #(parameter
										 SKIP_CNT_MAX = 3
										)
			 (
				 input wire clk,
				 input wire gen,
				 input wire ocd,
				 output wire out
			 );

int_gen i(
					.clk(clk),
					.freq_par(8'd1),	// 100 -> 1 MHz -> 1us
					.pw_par(8'd50),
					.out(int_wire)
				);

edge_det gen_p(.clk(clk), .sgn(gen), .out_p(gen_edge_p));

sync gen_d(
			 .clk(clk),
			 .data_raw(gen),
			 .data(gen_del)
		 );

typedef enum { STATE_0, STATE_1 } State;

`reg(STATE_1) state = STATE_0;
`reg(SKIP_CNT_MAX) skip_cnt = SKIP_CNT_MAX;
reg ff = 0;

// state transition conditions
wire cond_1 = ocd,
		 cond_0 = !skip_cnt;

always @(posedge clk) begin
	// state values
	case(state)
		STATE_0: if (gen_edge_p) ff <= !int_wire;
		STATE_1: if (gen_edge_p && skip_cnt) begin
				ff <= 0;
				skip_cnt <= skip_cnt - 1;
			end
	endcase

	// state transitions
	case(state)
		STATE_0: if (cond_1) state <= STATE_1;
		STATE_1: if (cond_0) begin
				state <= STATE_0;
				skip_cnt <= SKIP_CNT_MAX;
			end
	endcase
end

assign out = ff && gen_del;

endmodule

dist/selector.sv
`include "./modules/defines.sv"
module edge_det_160494775758805999572650583376
			 (
				 input wire clk,
				 input wire sgn,
				 output wire out_p,
				 output wire out_n,
				 output wire out
			 );

reg sgn_pre = 0;

assign out_p = sgn && ~sgn_pre,
			 out_n = ~sgn && sgn_pre,
			 out = sgn ^ sgn_pre;

always @(posedge clk)
	if (out) sgn_pre <= sgn;

endmodule


	module selector #(parameter
										CLK_MHZ = 100,
										PERIODS_TO_SWITCH = 4,
										RESET_TIMEOUT_US = 4
									 )
	(
		input wire clk,
		input wire gen,
		input wire fb,
		output wire out
	);

typedef enum { STATE_0, STATE_1 } State;

localparam TIMEOUT_CNT_MAX = CLK_MHZ * PERIODS_TO_SWITCH;

`reg(TIMEOUT_CNT_MAX) timeout_cnt = TIMEOUT_CNT_MAX - 1;
`reg(PERIODS_TO_SWITCH) per_to_sw_cnt = PERIODS_TO_SWITCH;
`reg(STATE_1) state = STATE_0;

edge_det_160494775758805999572650583376 edge_det_gen(.clk(clk), .sgn(gen), .out_n(gen_edge_n));
edge_det_160494775758805999572650583376 edge_det_fb(.clk(clk), .sgn(fb), .out_n(fb_edge_n));

// state transition conditions
wire cond_1 = !per_to_sw_cnt && fb_edge_n,	// some gen periods passed
		 cond_0 = !timeout_cnt && !gen;	// no signal on fb input

always @(posedge clk) begin
	// state values
	case(state)
		STATE_0: if (gen_edge_n) per_to_sw_cnt <= per_to_sw_cnt ? per_to_sw_cnt - 1 : PERIODS_TO_SWITCH;
		STATE_1: if (fb) timeout_cnt <= TIMEOUT_CNT_MAX - 1;
			else if (timeout_cnt) timeout_cnt <= timeout_cnt - 1;
	endcase

	// state transitions
	case(state)
		STATE_0: if (cond_1) state <= STATE_1;
		STATE_1: if (cond_0) begin
				state <= STATE_0;
				timeout_cnt <= TIMEOUT_CNT_MAX - 1;
			end
	endcase
end

assign out = state == STATE_0 ? gen : fb;

endmodule

src/pred.sv
`include "./modules/defines.sv"
`include "./modules/sync.sv"

module pred #(parameter
							PRED_PARAMETER = 255
						 )
			 (
				 input wire clk,
				 input wire sgn,
				 input `wire(PRED_PARAMETER) shift,
				 output reg sgn_pre = 0
			 );

// cdc synchronizer
sync #(.WIDTH(1))
		 s1(
			 .clk(clk),
			 .data_raw(sgn),
			 .data(sgn_s)
		 );

`reg(PRED_PARAMETER) cnt;
initial cnt = shift;

always @(posedge clk) begin
	if (sgn_s ^ sgn_pre) begin
		if (cnt) cnt <= cnt - 1;
		else begin
			cnt <= shift - 1;
			sgn_pre <= sgn_s;
		end
	end
end

endmodule

src/ref_gen.sv
`include "./modules/defines.sv"

module ref_gen #(parameter
								 CLK_MHZ = 100,
								 FREQ_MID_KHZ = 200,
								 GEN_PARAMETER = 255
								)
			 (
				 input wire clk,
				 input `wire(GEN_PARAMETER) inp,
				 output reg out = 0
			 );

localparam CNT_MID = `div(500 * CLK_MHZ, FREQ_MID_KHZ) - `div(GEN_PARAMETER, 2);

`reg(GEN_PARAMETER) gen_param;
initial gen_param = inp;

`reg(CNT_MID + GEN_PARAMETER - 1) cnt = 0;

always @(posedge clk) begin
	if (cnt) cnt <= cnt - 1;
	else begin
		cnt <= CNT_MID + gen_param - 1;
		out <= ~out;
	end
end

endmodule

entry.sv
`include "common.sv"

// 9600 Hz uart module uses 54 LE


module entry (
				 input wire clk,
				 input wire uart_data,
				 output `wire_2d(sh_reg, CONF_PAR_MAX, CONF_PAR_4),
				 //output wire[7:0] storage,
				 //output wire[1:0] state

				 output wire gen_out,

				 input wire fb_in,
				 output wire fb_out,

				 output wire sel_out,

				 input wire int_ocd,
				 output wire int_out,

				 output wire ocd_lvl_out
			 );

ref_gen rg1(
					.clk(clk),
					.inp(8'd0),
					.out(gen_out)
				);

pred p1(
			 .clk(clk),
			 .sgn(fb_in),
			 .shift(8'd30),
			 .sgn_pre(fb_out)
		 );

selector s1(
					 .clk(clk),
					 .gen(gen_out),
					 .fb(fb_out),
					 .out(sel_out)
				 );

interrupter i1(
							.clk(clk),
							.gen(sel_out),
							.ocd(int_ocd),
							.out(int_out)
						);

ocd_lvl #(.FREQ_KHZ(1000))
				o(
					.clk(clk),
					.pw_par(7'd87),
					.out(ocd_lvl_out)
				);

/*
uart #(
			 .CONF_PAR_MAX(CONF_PAR_MAX),
			 .FRAME_CNT_MAX_1(FRAME_CNT_MAX_1),
			 .FRAME_CNT_MAX_2(FRAME_CNT_MAX_2),
			 .DATA_BIT_CNT_MAX(DATA_BIT_CNT_MAX)
		 ) uart_ins(
			 .clk(clk),
			 .uart_data(uart_data),
			 .sh_reg(sh_reg)
			 //.storage(storage),
			 //.state(state)
		 );
*/

endmodule

tb.sv
`timescale 1ns/1ns
`include "entry.sv"

module test_entry;

reg clk_tb, uart_data_tb, uart_clk_tb;
wire is_data_ready_tb, out_tb;
`wire_2d(sh_reg_tb, CONF_PAR_MAX, CONF_PAR_4);
`wire(CONF_PAR_MAX) sh_0, sh_1, sh_2, sh_3, sh_4;
//wire[7:0] storage_tb;
//wire[1:0] state_tb;
wire gen_out_tb, fb_in_tb, fb_out_tb, sel_out_tb, int_ocd_tb, int_out_tb, ocd_lvl_out_tb;
reg fb_tb = 0, fb_mask = 1, ocd_tb = 0;

assign sh_0 = sh_reg_tb[0],
			 sh_1 = sh_reg_tb[1],
			 sh_2 = sh_reg_tb[2],
			 sh_3 = sh_reg_tb[3],
			 sh_4 = sh_reg_tb[4],

			 fb_in_tb = fb_tb && fb_mask,
			 int_ocd_tb = ocd_tb;


entry entry_inst(
				.clk(clk_tb),
				.uart_data(uart_data_tb),
				.sh_reg(sh_reg_tb),
				//.storage(storage_tb),
				//.state(state_tb)

				.gen_out(gen_out_tb),

				.fb_in(fb_in_tb),
				.fb_out(fb_out_tb),

				.sel_out(sel_out_tb),

				.int_ocd(int_ocd_tb),
				.int_out(int_out_tb),

				.ocd_lvl_out(ocd_lvl_out_tb)
			);

localparam //test_data = 49'b0_00101100_10_01001100_10_00101100_10_01001100_10_00101100, // 42424
					 test_data = 69'b0_11101100_10_01001100_10_00101100_10_01001100_10_00101100_10_00101100_10_10101100, // 72424_45
					 packet_size = $bits(test_data);

// clk
always #CLK_FRAME_TB clk_tb = ~clk_tb;
always #FRAME_TB uart_clk_tb = ~uart_clk_tb;

initial #(2 * (packet_size + 2) * FRAME_TB) $finish;

initial begin
	clk_tb = 0;
	uart_data_tb = 1;
	uart_clk_tb = 0;

	for (int i = packet_size; i > 0; i--) begin
		#(2 * FRAME_TB) uart_data_tb = test_data[i-1];
		if (i == 1) #(2 * FRAME_TB) uart_data_tb = 1;
	end
end


// fb and ocd
int i = 0;

initial begin
	#1050;
	while (1'b1) begin
		#1250 fb_tb = ~fb_tb;
		i++;
		ocd_tb = (i == 6) || (i == 89) ? 1 : 0;
	end
end

initial begin
	#1050;
	while (1'b1) begin
		#(24 * 1250) fb_mask = ~fb_mask;
	end
end

// creating VCD file for signal analysis
initial begin
	$dumpfile("out.vcd");
	$dumpvars(0, test_entry);
end

// displaying meaning signals
initial $monitor(
		$stime,,
		clk_tb,,
		uart_clk_tb,,
		uart_data_tb,,
		sh_0,,
		sh_1,,
		sh_2,,
		sh_3,,
		sh_4,,
		out_tb,,
		//storage_tb,,
		//state_tb

		gen_out_tb,,

		fb_in_tb,,
		fb_out_tb,,

		sel_out_tb,,

		int_ocd_tb,,
		int_out_tb,,

		ocd_lvl_out_tb
	);

endmodule

out.vcd
$date
	Mon Nov 09 21:49:20 2020
$end
$version
	Icarus Verilog
$end
$timescale
	1ns
$end
$scope module test_entry $end
$var wire 1 ! fb_in_tb $end
$var wire 1 " out_tb $end
$var wire 8 # sh_0 [7:0] $end
$var wire 8 $ sh_1 [7:0] $end
$var wire 8 % sh_2 [7:0] $end
$var wire 8 & sh_3 [7:0] $end
$var wire 8 ' sh_4 [7:0] $end
$var wire 1 ( sel_out_tb $end
$var wire 1 ) ocd_lvl_out_tb $end
$var wire 1 * int_out_tb $end
$var wire 1 + int_ocd_tb $end
$var wire 1 , gen_out_tb $end
$var wire 1 - fb_out_tb $end
$var reg 1 . clk_tb $end
$var reg 1 / fb_mask $end
$var reg 1 0 fb_tb $end
$var reg 1 + ocd_tb $end
$var reg 1 1 uart_clk_tb $end
$var reg 1 2 uart_data_tb $end
$var integer 32 3 i [31:0] $end
$scope module entry_inst $end
$var wire 1 . clk $end
$var wire 1 ! fb_in $end
$var wire 1 + int_ocd $end
$var wire 1 2 uart_data $end
$var wire 1 ( sel_out $end
$var wire 1 ) ocd_lvl_out $end
$var wire 1 * int_out $end
$var wire 1 , gen_out $end
$var wire 1 - fb_out $end
$scope module i1 $end
$var wire 1 . clk $end
$var wire 1 4 cond_1 $end
$var wire 1 + ocd $end
$var wire 1 * out $end
$var wire 1 5 int_wire $end
$var wire 1 6 gen_edge_p $end
$var wire 1 7 gen_del $end
$var wire 1 ( gen $end
$var wire 1 8 cond_0 $end
$var reg 1 9 ff $end
$var reg 2 : skip_cnt [1:0] $end
$var reg 1 ; state $end
$scope module gen_d $end
$var wire 1 . clk $end
$var wire 1 ( data_raw $end
$var reg 1 7 data $end
$var reg 1 < internal $end
$upscope $end
$scope module gen_p $end
$var wire 1 . clk $end
$var wire 1 = out $end
$var wire 1 > out_n $end
$var wire 1 6 out_p $end
$var wire 1 ( sgn $end
$var reg 1 ? sgn_pre $end
$upscope $end
$scope module i $end
$var wire 1 . clk $end
$var wire 8 @ freq_par [7:0] $end
$var wire 8 A pw_par [7:0] $end
$var wire 1 5 out $end
$var reg 14 B cnt [13:0] $end
$upscope $end
$upscope $end
$scope module o $end
$var wire 1 . clk $end
$var wire 7 C pw_par [6:0] $end
$var wire 1 ) out $end
$var reg 7 D cnt [6:0] $end
$upscope $end
$scope module p1 $end
$var wire 1 . clk $end
$var wire 1 ! sgn $end
$var wire 8 E shift [7:0] $end
$var reg 8 F cnt [7:0] $end
$var reg 1 - sgn_pre $end
$upscope $end
$scope module rg1 $end
$var wire 1 . clk $end
$var wire 8 G inp [7:0] $end
$var reg 9 H cnt [8:0] $end
$var reg 8 I gen_param [7:0] $end
$var reg 1 , out $end
$upscope $end
$scope module s1 $end
$var wire 1 . clk $end
$var wire 1 J cond_0 $end
$var wire 1 K cond_1 $end
$var wire 1 - fb $end
$var wire 1 , gen $end
$var wire 1 ( out $end
$var wire 1 L gen_edge_n $end
$var wire 1 M fb_edge_n $end
$var reg 3 N per_to_sw_cnt [2:0] $end
$var reg 1 O state $end
$var reg 9 P timeout_cnt [8:0] $end
$scope module edge_det_fb $end
$var wire 1 . clk $end
$var wire 1 Q out $end
$var wire 1 M out_n $end
$var wire 1 R out_p $end
$var wire 1 - sgn $end
$var reg 1 S sgn_pre $end
$upscope $end
$scope module edge_det_gen $end
$var wire 1 . clk $end
$var wire 1 T out $end
$var wire 1 L out_n $end
$var wire 1 U out_p $end
$var wire 1 , sgn $end
$var reg 1 V sgn_pre $end
$upscope $end
$upscope $end
$upscope $end
$scope begin $ivl_for_loop1 $end
$var integer 32 W i [31:0] $end
$upscope $end
$upscope $end
$enddefinitions $end
#0
$dumpvars
b1000101 W
0V
0U
0T
0S
0R
0Q
b110001111 P
0O
b100 N
0M
0L
0K
0J
b0 I
b0 H
b0 G
b11110 F
b11110 E
b1100011 D
b1010111 C
b0 B
b110010 A
b1 @
0?
0>
0=
0<
0;
b11 :
09
08
07
06
15
04
b0 3
12
01
00
1/
0.
0-
0,
0+
0*
0)
0(
bz '
bz &
bz %
bz $
bz #
z"
0!
$end
#5
1=
16
1(
1U
1T
1,
b1111100 H
05
b10011100001111 B
b1100010 D
1.
#10
0.
#15
06
0U
0=
0T
b1100001 D
19
1<
1?
b10011100001110 B
1V
b1111011 H
1.
#20
0.
#25
1*
b1111010 H
b10011100001101 B
17
b1100000 D
1.
#30
0.
#35
b1011111 D
b10011100001100 B
b1111001 H
1.
#40
0.
#45
b1111000 H
b10011100001011 B
b1011110 D
1.
#50
0.
#55
b1011101 D
b10011100001010 B
b1110111 H
1.
#60
0.
#65
b1110110 H
b10011100001001 B
b1011100 D
1.
#70
0.
#75
b1011011 D
b10011100001000 B
b1110101 H
1.
#80
0.
#85
b1110100 H
b10011100000111 B
b1011010 D
1.
#90
0.
#95
b1011001 D
b10011100000110 B
b1110011 H
1.
#100
0.
#105
b1110010 H
b10011100000101 B
b1011000 D
1.
#110
0.
#115
b1010111 D
b10011100000100 B
b1110001 H
1.
#120
0.
#125
b1110000 H
b10011100000011 B
1)
b1010110 D
1.
#130
0.
#135
b1010101 D
b10011100000010 B
b1101111 H
1.
#140
0.
#145
b1101110 H
b10011100000001 B
b1010100 D
1.
#150
0.
#155
b1010011 D
b10011100000000 B
b1101101 H
1.
#160
0.
#165
b1101100 H
b10011011111111 B
b1010010 D
1.
#170
0.
#175
b1010001 D
b10011011111110 B
b1101011 H
1.
#180
0.
#185
b1101010 H
b10011011111101 B
b1010000 D
1.
#190
0.
#195
b1001111 D
b10011011111100 B
b1101001 H
1.
#200
0.
#205
b1101000 H
b10011011111011 B
b1001110 D
1.
#210
0.
#215
b1001101 D
b10011011111010 B
b1100111 H
1.
#220
0.
#225
b1100110 H
b10011011111001 B
b1001100 D
1.
#230
0.
#235
b1001011 D
b10011011111000 B
b1100101 H
1.
#240
0.
#245
b1100100 H
b10011011110111 B
b1001010 D
1.
#250
0.
#255
b1001001 D
b10011011110110 B
b1100011 H
1.
#260
0.
#265
b1100010 H
b10011011110101 B
b1001000 D
1.
#270
0.
#275
b1000111 D
b10011011110100 B
b1100001 H
1.
#280
0.
#285
b1100000 H
b10011011110011 B
b1000110 D
1.
#290
0.
#295
b1000101 D
b10011011110010 B
b1011111 H
1.
#300
0.
#305
b1011110 H
b10011011110001 B
b1000100 D
1.
#310
0.
#315
b1000011 D
b10011011110000 B
b1011101 H
1.
#320
0.
#325
b1011100 H
b10011011101111 B
b1000010 D
1.
#330
0.
#335
b1000001 D
b10011011101110 B
b1011011 H
1.
#340
0.
#345
b1011010 H
b10011011101101 B
b1000000 D
1.
#350
0.
#355
b111111 D
b10011011101100 B
b1011001 H
1.
#360
0.
#365
b1011000 H
b10011011101011 B
b111110 D
1.
#370
0.
#375
b111101 D
b10011011101010 B
b1010111 H
1.
#380
0.
#385
b1010110 H
b10011011101001 B
b111100 D
1.
#390
0.
#395
b111011 D
b10011011101000 B
b1010101 H
1.
#400
0.
#405
b1010100 H
b10011011100111 B
b111010 D
1.
#410
0.
#415
b111001 D
b10011011100110 B
b1010011 H
1.
#420
0.
#425
b1010010 H
b10011011100101 B
b111000 D
1.
#430
0.
#435
b110111 D
b10011011100100 B
b1010001 H
1.
#440
0.
#445
b1010000 H
b10011011100011 B
b110110 D
1.
#450
0.
#455
b110101 D
b10011011100010 B
b1001111 H
1.
#460
0.
#465
b1001110 H
b10011011100001 B
b110100 D
1.
#470
0.
#475
b110011 D
b10011011100000 B
b1001101 H
1.
#480
0.
#485
b1001100 H
b10011011011111 B
b110010 D
1.
#490
0.
#495
b110001 D
b10011011011110 B
b1001011 H
1.
#500
0.
#505
b1001010 H
b10011011011101 B
b110000 D
1.
#510
0.
#515
b101111 D
b10011011011100 B
b1001001 H
1.
#520
0.
#525
b1001000 H
b10011011011011 B
b101110 D
1.
#530
0.
#535
b101101 D
b10011011011010 B
b1000111 H
1.
#540
0.
#545
b1000110 H
b10011011011001 B
b101100 D
1.
#550
0.
#555
b101011 D
b10011011011000 B
b1000101 H
1.
#560
0.
#565
b1000100 H
b10011011010111 B
b101010 D
1.
#570
0.
#575
b101001 D
b10011011010110 B
b1000011 H
1.
#580
0.
#585
b1000010 H
b10011011010101 B
b101000 D
1.
#590
0.
#595
b100111 D
b10011011010100 B
b1000001 H
1.
#600
0.
#605
b1000000 H
b10011011010011 B
b100110 D
1.
#610
0.
#615
b100101 D
b10011011010010 B
b111111 H
1.
#620
0.
#625
b111110 H
b10011011010001 B
b100100 D
1.
#630
0.
#635
b100011 D
b10011011010000 B
b111101 H
1.
#640
0.
#645
b111100 H
b10011011001111 B
b100010 D
1.
#650
0.
#655
b100001 D
b10011011001110 B
b111011 H
1.
#660
0.
#665
b111010 H
b10011011001101 B
b100000 D
1.
#670
0.
#675
b11111 D
b10011011001100 B
b111001 H
1.
#680
0.
#685
b111000 H
b10011011001011 B
b11110 D
1.
#690
0.
#695
b11101 D
b10011011001010 B
b110111 H
1.
#700
0.
#705
b110110 H
b10011011001001 B
b11100 D
1.
#710
0.
#715
b11011 D
b10011011001000 B
b110101 H
1.
#720
0.
#725
b110100 H
b10011011000111 B
b11010 D
1.
#730
0.
#735
b11001 D
b10011011000110 B
b110011 H
1.
#740
0.
#745
b110010 H
b10011011000101 B
b11000 D
1.
#750
0.
#755
b10111 D
b10011011000100 B
b110001 H
1.
#760
0.
#765
b110000 H
b10011011000011 B
b10110 D
1.
#770
0.
#775
b10101 D
b10011011000010 B
b101111 H
1.
#780
0.
#785
b101110 H
b10011011000001 B
b10100 D
1.
#790
0.
#795
b10011 D
b10011011000000 B
b101101 H
1.
#800
0.
#805
b101100 H
b10011010111111 B
b10010 D
1.
#810
0.
#815
b10001 D
b10011010111110 B
b101011 H
1.
#820
0.
#825
b101010 H
b10011010111101 B
b10000 D
1.
#830
0.
#835
b1111 D
b10011010111100 B
b101001 H
1.
#840
0.
#845
b101000 H
b10011010111011 B
b1110 D
1.
#850
0.
#855
b1101 D
b10011010111010 B
b100111 H
1.
#860
0.
#865
b100110 H
b10011010111001 B
b1100 D
1.
#870
0.
#875
b1011 D
b10011010111000 B
b100101 H
1.
#880
0.
#885
b100100 H
b10011010110111 B
b1010 D
1.
#890
0.
#895
b1001 D
b10011010110110 B
b100011 H
1.
#900
0.
#905
b100010 H
b10011010110101 B
b1000 D
1.
#910
0.
#915
b111 D
b10011010110100 B
b100001 H
1.
#920
0.
#925
b100000 H
b10011010110011 B
b110 D
1.
#930
0.
#935
b101 D
b10011010110010 B
b11111 H
1.
#940
0.
#945
b11110 H
b10011010110001 B
b100 D
1.
#950
0.
#955
b11 D
b10011010110000 B
b11101 H
1.
#960
0.
#965
b11100 H
b10011010101111 B
b10 D
1.
#970
0.
#975
b1 D
b10011010101110 B
b11011 H
1.
#980
0.
#985
b11010 H
b10011010101101 B
b0 D
1.
#990
0.
#995
0)
b1100011 D
b10011010101100 B
b11001 H
1.
#1000
0.
#1005
b11000 H
b10011010101011 B
b1100010 D
1.
#1010
0.
#1015
b1100001 D
b10011010101010 B
b10111 H
1.
#1020
0.
#1025
b10110 H
b10011010101001 B
b1100000 D
1.
#1030
0.
#1035
b1011111 D
b10011010101000 B
b10101 H
1.
#1040
0.
#1045
b10100 H
b10011010100111 B
b1011110 D
1.
#1050
0.
#1055
b1011101 D
b10011010100110 B
b10011 H
1.
#1060
0.
#1065
b10010 H
b10011010100101 B
b1011100 D
1.
#1070
0.
#1075
b1011011 D
b10011010100100 B
b10001 H
1.
#1080
0.
#1085
b10000 H
b10011010100011 B
b1011010 D
1.
#1090
0.
#1095
b1011001 D
b10011010100010 B
b1111 H
1.
#1100
0.
#1105
b1110 H
b10011010100001 B
b1011000 D
1.
#1110
0.
#1115
b1010111 D
b10011010100000 B
b1101 H
1.
#1120
0.
#1125
b1100 H
b10011010011111 B
1)
b1010110 D
1.
#1130
0.
#1135
b1010101 D
b10011010011110 B
b1011 H
1.
#1140
0.
#1145
b1010 H
b10011010011101 B
b1010100 D
1.
#1150
0.
#1155
b1010011 D
b10011010011100 B
b1001 H
1.
#1160
0.
#1165
b1000 H
b10011010011011 B
b1010010 D
1.
#1170
0.
#1175
b1010001 D
b10011010011010 B
b111 H
1.
#1180
0.
#1185
b110 H
b10011010011001 B
b1010000 D
1.
#1190
0.
#1195
b1001111 D
b10011010011000 B
b101 H
1.
#1200
0.
#1205
b100 H
b10011010010111 B
b1001110 D
1.
#1210
0.
#1215
b1001101 D
b10011010010110 B
b11 H
1.
#1220
0.
#1225
b10 H
b10011010010101 B
b1001100 D
1.
#1230
0.
#1235
b1001011 D
b10011010010100 B
b1 H
1.
#1240
0.
#1245
b0 H
b10011010010011 B
b1001010 D
1.
#1250
0.
#1255
1>
1=
1L
0(
1T
b1001001 D
b10011010010010 B
0,
b1111100 H
1.
#1260
0.
#1265
0T
0L
0=
0>
b1111011 H
0V
b11 N
b10011010010001 B
0?
0<
b1001000 D
1.
#1270
0.
#1275
0*
b1000111 D
07
b10011010010000 B
b1111010 H
1.
#1280
0.
#1285
b1111001 H
b10011010001111 B
b1000110 D
1.
#1290
0.
#1295
b1000101 D
b10011010001110 B
b1111000 H
1.
#1300
0.
#1305
b1110111 H
b10011010001101 B
b1000100 D
1.
#1310
0.
#1315
b1000011 D
b10011010001100 B
b1110110 H
1.
#1320
0.
#1325
b1110101 H
b10011010001011 B
b1000010 D
1.
#1330
0.
#1335
b1000001 D
b10011010001010 B
b1110100 H
1.
#1340
0.
#1345
b1110011 H
b10011010001001 B
b1000000 D
1.
#1350
0.
#1355
b111111 D
b10011010001000 B
b1110010 H
1.
#1360
0.
#1365
b1110001 H
b10011010000111 B
b111110 D
1.
#1370
0.
#1375
b111101 D
b10011010000110 B
b1110000 H
1.
#1380
0.
#1385
b1101111 H
b10011010000101 B
b111100 D
1.
#1390
0.
#1395
b111011 D
b10011010000100 B
b1101110 H
1.
#1400
0.
#1405
b1101101 H
b10011010000011 B
b111010 D
1.
#1410
0.
#1415
b111001 D
b10011010000010 B
b1101100 H
1.
#1420
0.
#1425
b1101011 H
b10011010000001 B
b111000 D
1.
#1430
0.
#1435
b110111 D
b10011010000000 B
b1101010 H
1.
#1440
0.
#1445
b1101001 H
b10011001111111 B
b110110 D
1.
#1450
0.
#1455
b110101 D
b10011001111110 B
b1101000 H
1.
#1460
0.
#1465
b1100111 H
b10011001111101 B
b110100 D
1.
#1470
0.
#1475
b110011 D
b10011001111100 B
b1100110 H
1.
#1480
0.
#1485
b1100101 H
b10011001111011 B
b110010 D
1.
#1490
0.
#1495
b110001 D
b10011001111010 B
b1100100 H
1.
#1500
0.
#1505
b1100011 H
b10011001111001 B
b110000 D
1.
#1510
0.
#1515
b101111 D
b10011001111000 B
b1100010 H
1.
#1520
0.
#1525
b1100001 H
b10011001110111 B
b101110 D
1.
#1530
0.
#1535
b101101 D
b10011001110110 B
b1100000 H
1.
#1540
0.
#1545
b1011111 H
b10011001110101 B
b101100 D
1.
#1550
0.
#1555
b101011 D
b10011001110100 B
b1011110 H
1.
#1560
0.
#1563
11
#1565
b1011101 H
b10011001110011 B
b101010 D
1.
#1570
0.
#1575
b101001 D
b10011001110010 B
b1011100 H
1.
#1580
0.
#1585
b1011011 H
b10011001110001 B
b101000 D
1.
#1590
0.
#1595
b100111 D
b10011001110000 B
b1011010 H
1.
#1600
0.
#1605
b1011001 H
b10011001101111 B
b100110 D
1.
#1610
0.
#1615
b100101 D
b10011001101110 B
b1011000 H
1.
#1620
0.
#1625
b1010111 H
b10011001101101 B
b100100 D
1.
#1630
0.
#1635
b100011 D
b10011001101100 B
b1010110 H
1.
#1640
0.
#1645
b1010101 H
b10011001101011 B
b100010 D
1.
#1650
0.
#1655
b100001 D
b10011001101010 B
b1010100 H
1.
#1660
0.
#1665
b1010011 H
b10011001101001 B
b100000 D
1.
#1670
0.
#1675
b11111 D
b10011001101000 B
b1010010 H
1.
#1680
0.
#1685
b1010001 H
b10011001100111 B
b11110 D
1.
#1690
0.
#1695
b11101 D
b10011001100110 B
b1010000 H
1.
#1700
0.
#1705
b1001111 H
b10011001100101 B
b11100 D
1.
#1710
0.
#1715
b11011 D
b10011001100100 B
b1001110 H
1.
#1720
0.
#1725
b1001101 H
b10011001100011 B
b11010 D
1.
#1730
0.
#1735
b11001 D
b10011001100010 B
b1001100 H
1.
#1740
0.
#1745
b1001011 H
b10011001100001 B
b11000 D
1.
#1750
0.
#1755
b10111 D
b10011001100000 B
b1001010 H
1.
#1760
0.
#1765
b1001001 H
b10011001011111 B
b10110 D
1.
#1770
0.
#1775
b10101 D
b10011001011110 B
b1001000 H
1.
#1780
0.
#1785
b1000111 H
b10011001011101 B
b10100 D
1.
#1790
0.
#1795
b10011 D
b10011001011100 B
b1000110 H
1.
#1800
0.
#1805
b1000101 H
b10011001011011 B
b10010 D
1.
#1810
0.
#1815
b10001 D
b10011001011010 B
b1000100 H
1.
#1820
0.
#1825
b1000011 H
b10011001011001 B
b10000 D
1.
#1830
0.
#1835
b1111 D
b10011001011000 B
b1000010 H
1.
#1840
0.
#1845
b1000001 H
b10011001010111 B
b1110 D
1.
#1850
0.
#1855
b1101 D
b10011001010110 B
b1000000 H
1.
#1860
0.
#1865
b111111 H
b10011001010101 B
b1100 D
1.
#1870
0.
#1875
b1011 D
b10011001010100 B
b111110 H
1.
#1880
0.
#1885
b111101 H
b10011001010011 B
b1010 D
1.
#1890
0.
#1895
b1001 D
b10011001010010 B
b111100 H
1.
#1900
0.
#1905
b111011 H
b10011001010001 B
b1000 D
1.
#1910
0.
#1915
b111 D
b10011001010000 B
b111010 H
1.
#1920
0.
#1925
b111001 H
b10011001001111 B
b110 D
1.
#1930
0.
#1935
b101 D
b10011001001110 B
b111000 H
1.
#1940
0.
#1945
b110111 H
b10011001001101 B
b100 D
1.
#1950
0.
#1955
b11 D
b10011001001100 B
b110110 H
1.
#1960
0.
#1965
b110101 H
b10011001001011 B
b10 D
1.
#1970
0.
#1975
b1 D
b10011001001010 B
b110100 H
1.
#1980
0.
#1985
b110011 H
b10011001001001 B
b0 D
1.
#1990
0.
#1995
0)
b1100011 D
b10011001001000 B
b110010 H
1.
#2000
0.
#2005
b110001 H
b10011001000111 B
b1100010 D
1.
#2010
0.
