common.sv
`include "modules/include_all.sv"

/*
real uart frequency is 9600 Hz
assume 960 kHz for faster simulation
*/

localparam 	GEN_CLK_FREQ = 100_000_000,
						TB_CLK_FREQ = 1_000_000_000,
						UART_FREQ = 960_000,

						FRAME_FREQ = 2 * UART_FREQ,
						FRAME = `div(GEN_CLK_FREQ, FRAME_FREQ),
						FRAME_TB = `div(TB_CLK_FREQ, FRAME_FREQ),
						CLK_FRAME_TB = `div(TB_CLK_FREQ, (2 * GEN_CLK_FREQ)),

						CONF_PAR_MAX = 255,
						FRAME_CNT_MAX_1 = 3 * FRAME,
						FRAME_CNT_MAX_2 = 2 * FRAME,
						DATA_BIT_CNT_MAX = 7;

modules/defines.sv
`define reg(val) reg[$clog2(val+1)-1:0]
`define wire(val) wire[$clog2(val+1)-1:0]

`define div(A, B) A / B + (2*(A % B) >= B ? 1 : 0)

modules/edge_det.sv
module edge_det
			 (
				 input wire clk,
				 input wire sgn,
				 output wire out_p,
				 output wire out_n,
				 output wire out
			 );

reg sgn_pre = 0;

assign out_p = sgn && ~sgn_pre,
			 out_n = ~sgn && sgn_pre,
			 out = sgn ^ sgn_pre;

always @(posedge clk)
	if (out) sgn_pre <= sgn;

endmodule

modules/uart.sv
`include "modules/defines.sv"
`include "modules/edge_det.sv"

/*
0 - ref_gen
1 - phase_shift
2 - ocd_lvl
3 - inter_freq
4 - inter_duty
*/



typedef enum { STATE_0, STATE_1, STATE_2 } State;
typedef enum { CONF_PAR_0, CONF_PAR_1, CONF_PAR_2, CONF_PAR_3, CONF_PAR_4 } Conf_par;

module uart #(parameter
							CONF_PAR_MAX = 255,
							FRAME_CNT_MAX_1 = 3 * 52,
							FRAME_CNT_MAX_2 = 2 * 52,
							DATA_BIT_CNT_MAX = 7
						 )
			 (
				 input wire clk,
				 input wire uart_data,
				 output `reg_2d(sh_reg, CONF_PAR_MAX, CONF_PAR_4),
				 output `reg(CONF_PAR_MAX) storage = 0,
				 output `reg(STATE_2) state = STATE_0
			 );

// initializing sh_reg with zeroes
initial for(int i = 0; i <= CONF_PAR_4; i++) sh_reg[i] = 0;

`reg(FRAME_CNT_MAX_1) frame_cnt = FRAME_CNT_MAX_1;
//`reg(STATE_2) state = STATE_0;
`reg(DATA_BIT_CNT_MAX) data_bit_cnt = DATA_BIT_CNT_MAX;
`reg(CONF_PAR_4) conf_par_cnt = CONF_PAR_4;
//`reg(CONF_PAR_MAX) storage = 0;

wire data_edge_n;

// state transition conditions
wire cond_1 = data_edge_n,	// transmission start
		 cond_2 = !frame_cnt,	// first data bit
		 cond_0 = !data_bit_cnt;	// last data bit

edge_det edge_det_ins(.clk(clk), .sgn(uart_data), .out_n(data_edge_n));

always @(posedge clk) begin
	// state values
	case(state)
		STATE_1: frame_cnt <= frame_cnt ? frame_cnt - 1 : FRAME_CNT_MAX_2;

		STATE_2: if (frame_cnt) frame_cnt <= frame_cnt - 1;
			else begin
				frame_cnt <= FRAME_CNT_MAX_2;
				data_bit_cnt <= data_bit_cnt - 1;
				storage <= {uart_data, storage[`width(CONF_PAR_MAX)-1:1]};
			end
	endcase

	// state transitions
	case(state)
		STATE_0: if (cond_1) state <= STATE_1;
		STATE_1: if (cond_2) begin
				state <= STATE_2;
				storage <= {uart_data, storage[`width(CONF_PAR_MAX)-1:1]};
			end
		STATE_2: if (cond_0) begin
				state <= STATE_0;
				sh_reg[conf_par_cnt] <= storage;
				conf_par_cnt <= conf_par_cnt ? conf_par_cnt - 1 : CONF_PAR_4;
				frame_cnt <= FRAME_CNT_MAX_1;
				data_bit_cnt <= DATA_BIT_CNT_MAX;
			end
	endcase
end

endmodule

entry.sv
`include "common.sv"

// 9600 Hz uart module uses 54 LE


module entry (
				 input wire clk,
				 input wire uart_data,
				 output `wire_2d(sh_reg, CONF_PAR_MAX, CONF_PAR_4),
				 output wire[7:0] storage,
				 output wire[1:0] state
			 );
/*
gen gen_ins(
			.clk(clk),
			.en(is_data_ready),
			.inp(storage),
			.out(out)
		);
*/
uart #(
			 .CONF_PAR_MAX(CONF_PAR_MAX),
			 .FRAME_CNT_MAX_1(FRAME_CNT_MAX_1),
			 .FRAME_CNT_MAX_2(FRAME_CNT_MAX_2),
			 .DATA_BIT_CNT_MAX(DATA_BIT_CNT_MAX)
		 ) uart_ins(
			 .clk(clk),
			 .uart_data(uart_data),
			 .sh_reg(sh_reg),
			 .storage(storage),
			 .state(state)
		 );


endmodule

tb.sv
`timescale 1ns/1ns
`include "entry.sv"

module test_entry;

reg clk_tb, uart_data_tb, uart_clk_tb;
wire is_data_ready_tb, out_tb;
`wire_2d(sh_reg_tb, CONF_PAR_MAX, CONF_PAR_4);
`wire(CONF_PAR_MAX) sh_0, sh_1, sh_2, sh_3, sh_4;
wire[7:0] storage_tb;
wire[1:0] state_tb;

assign sh_0 = sh_reg_tb[0],
			 sh_1 = sh_reg_tb[1],
			 sh_2 = sh_reg_tb[2],
			 sh_3 = sh_reg_tb[3],
			 sh_4 = sh_reg_tb[4];


entry entry_inst(
				.clk(clk_tb),
				.uart_data(uart_data_tb),
				.sh_reg(sh_reg_tb),
				.storage(storage_tb),
				.state(state_tb)
			);

localparam //test_data = 49'b0_00101100_10_01001100_10_00101100_10_01001100_10_00101100, // 42424
					 test_data = 69'b0_11101100_10_01001100_10_00101100_10_01001100_10_00101100_10_00101100_10_10101100, // 72424_45
					 packet_size = $bits(test_data);

// clk
always #CLK_FRAME_TB clk_tb = ~clk_tb;
always #FRAME_TB uart_clk_tb = ~uart_clk_tb;

initial #(2 * (packet_size + 2) * FRAME_TB) $finish;

initial begin
	clk_tb = 0;
	uart_data_tb = 1;
	uart_clk_tb = 0;

	for (int i = packet_size; i > 0; i--) begin
		#(2 * FRAME_TB) uart_data_tb = test_data[i-1];
		if (i == 1) #(2 * FRAME_TB) uart_data_tb = 1;
	end
end

// creating VCD file for signal analysis
initial begin
	$dumpfile("out.vcd");
	$dumpvars(0, test_entry);
end

// displaying meaning signals
initial $monitor(
		$stime,,
		clk_tb,,
		uart_clk_tb,,
		uart_data_tb,,
		sh_0,,
		sh_1,,
		sh_2,,
		sh_3,,
		sh_4,,
		out_tb,,
		storage_tb,,
		state_tb
	);

endmodule

out.vcd
$date
	Wed Aug 12 21:55:22 2020
$end
$version
	Icarus Verilog
$end
$timescale
	1ns
$end
$scope module test_entry $end
$var wire 1 ! out_tb $end
$var wire 8 " sh_0 [7:0] $end
$var wire 8 # sh_1 [7:0] $end
$var wire 8 $ sh_2 [7:0] $end
$var wire 8 % sh_3 [7:0] $end
$var wire 8 & sh_4 [7:0] $end
$var wire 8 ' storage_tb [7:0] $end
$var wire 2 ( state_tb [1:0] $end
$var reg 1 ) clk_tb $end
$var reg 1 * uart_clk_tb $end
$var reg 1 + uart_data_tb $end
$scope module entry_inst $end
$var wire 1 ) clk $end
$var wire 1 + uart_data $end
$var wire 8 , storage [7:0] $end
$var wire 2 - state [1:0] $end
$scope module uart_ins $end
$var wire 1 ) clk $end
$var wire 1 . cond_1 $end
$var wire 1 + uart_data $end
$var wire 1 / data_edge_n $end
$var wire 1 0 cond_2 $end
$var wire 1 1 cond_0 $end
$var reg 3 2 conf_par_cnt [2:0] $end
$var reg 3 3 data_bit_cnt [2:0] $end
$var reg 8 4 frame_cnt [7:0] $end
$var reg 2 5 state [1:0] $end
$var reg 8 6 storage [7:0] $end
$scope module edge_det_ins $end
$var wire 1 ) clk $end
$var wire 1 7 out $end
$var wire 1 / out_n $end
$var wire 1 8 out_p $end
$var wire 1 + sgn $end
$var reg 1 9 sgn_pre $end
$upscope $end
$scope begin $ivl_for_loop0 $end
$var integer 32 : i [31:0] $end
$upscope $end
$upscope $end
$upscope $end
$scope begin $ivl_for_loop1 $end
$var integer 32 ; i [31:0] $end
$upscope $end
$upscope $end
$enddefinitions $end
#0
$dumpvars
b1000101 ;
b101 :
09
18
17
b0 6
b0 5
b10011100 4
b111 3
b100 2
01
00
0/
0.
b0 -
b0 ,
1+
0*
0)
b0 (
b0 '
b0 &
b0 %
b0 $
b0 #
b0 "
z!
$end
#5
08
07
19
1)
#10
0)
#15
1)
#20
0)
#25
1)
#30
0)
#35
1)
#40
0)
#45
1)
#50
0)
#55
1)
#60
0)
#65
1)
#70
0)
#75
1)
#80
0)
#85
1)
#90
0)
#95
1)
#100
0)
#105
1)
#110
0)
#115
1)
#120
0)
#125
1)
#130
0)
#135
1)
#140
0)
#145
1)
#150
0)
#155
1)
#160
0)
#165
1)
#170
0)
#175
1)
#180
0)
#185
1)
#190
0)
#195
1)
#200
0)
#205
1)
#210
0)
#215
1)
#220
0)
#225
1)
#230
0)
#235
1)
#240
0)
#245
1)
#250
0)
#255
1)
#260
0)
#265
1)
#270
0)
#275
1)
#280
0)
#285
1)
#290
0)
#295
1)
#300
0)
#305
1)
#310
0)
#315
1)
#320
0)
#325
1)
#330
0)
#335
1)
#340
0)
#345
1)
#350
0)
#355
1)
#360
0)
#365
1)
#370
0)
#375
1)
#380
0)
#385
1)
#390
0)
#395
1)
#400
0)
#405
1)
#410
0)
#415
1)
#420
0)
#425
1)
#430
0)
#435
1)
#440
0)
#445
1)
#450
0)
#455
1)
#460
0)
#465
1)
#470
0)
#475
1)
#480
0)
#485
1)
#490
0)
#495
1)
#500
0)
#505
1)
#510
0)
#515
1)
#520
0)
#521
1*
#525
1)
#530
0)
#535
1)
#540
0)
#545
1)
#550
0)
#555
1)
#560
0)
#565
1)
#570
0)
#575
1)
#580
0)
#585
1)
#590
0)
#595
1)
#600
0)
#605
1)
#610
0)
#615
1)
#620
0)
#625
1)
#630
0)
#635
1)
#640
0)
#645
1)
#650
0)
#655
1)
#660
0)
#665
1)
#670
0)
#675
1)
#680
0)
#685
1)
#690
0)
#695
1)
#700
0)
#705
1)
#710
0)
#715
1)
#720
0)
#725
1)
#730
0)
#735
1)
#740
0)
#745
1)
#750
0)
#755
1)
#760
0)
#765
1)
#770
0)
#775
1)
#780
0)
#785
1)
#790
0)
#795
1)
#800
0)
#805
1)
#810
0)
#815
1)
#820
0)
#825
1)
#830
0)
#835
1)
#840
0)
#845
1)
#850
0)
#855
1)
#860
0)
#865
1)
#870
0)
#875
1)
#880
0)
#885
1)
#890
0)
#895
1)
#900
0)
#905
1)
#910
0)
#915
1)
#920
0)
#925
1)
#930
0)
#935
1)
#940
0)
#945
1)
#950
0)
#955
1)
#960
0)
#965
1)
#970
0)
#975
1)
#980
0)
#985
1)
#990
0)
#995
1)
#1000
0)
#1005
1)
#1010
0)
#1015
1)
#1020
0)
#1025
1)
#1030
0)
#1035
1)
#1040
0)
#1042
1.
1/
17
0*
b1000100 ;
0+
#1045
07
0.
0/
09
b1 (
b1 -
b1 5
1)
#1050
0)
#1055
b10011011 4
1)
#1060
0)
#1065
b10011010 4
1)
#1070
0)
#1075
b10011001 4
1)
#1080
0)
#1085
b10011000 4
1)
#1090
0)
#1095
b10010111 4
1)
#1100
0)
#1105
b10010110 4
1)
#1110
0)
#1115
b10010101 4
1)
#1120
0)
#1125
b10010100 4
1)
#1130
0)
#1135
b10010011 4
1)
#1140
0)
#1145
b10010010 4
1)
#1150
0)
#1155
b10010001 4
1)
#1160
0)
#1165
b10010000 4
1)
#1170
0)
#1175
b10001111 4
1)
#1180
0)
#1185
b10001110 4
1)
#1190
0)
#1195
b10001101 4
1)
#1200
0)
#1205
b10001100 4
1)
#1210
0)
#1215
b10001011 4
1)
#1220
0)
#1225
b10001010 4
1)
#1230
0)
#1235
b10001001 4
1)
#1240
0)
#1245
b10001000 4
1)
#1250
0)
#1255
b10000111 4
1)
#1260
0)
#1265
b10000110 4
1)
#1270
0)
#1275
b10000101 4
1)
#1280
0)
#1285
b10000100 4
1)
#1290
0)
#1295
b10000011 4
1)
#1300
0)
#1305
b10000010 4
1)
#1310
0)
#1315
b10000001 4
1)
#1320
0)
#1325
b10000000 4
1)
#1330
0)
#1335
b1111111 4
1)
#1340
0)
#1345
b1111110 4
1)
#1350
0)
#1355
b1111101 4
1)
#1360
0)
#1365
b1111100 4
1)
#1370
0)
#1375
b1111011 4
1)
#1380
0)
#1385
b1111010 4
1)
#1390
0)
#1395
b1111001 4
1)
#1400
0)
#1405
b1111000 4
1)
#1410
0)
#1415
b1110111 4
1)
#1420
0)
#1425
b1110110 4
1)
#1430
0)
#1435
b1110101 4
1)
#1440
0)
#1445
b1110100 4
1)
#1450
0)
#1455
b1110011 4
1)
#1460
0)
#1465
b1110010 4
1)
#1470
0)
#1475
b1110001 4
1)
#1480
0)
#1485
b1110000 4
1)
#1490
0)
#1495
b1101111 4
1)
#1500
0)
#1505
b1101110 4
1)
#1510
0)
#1515
b1101101 4
1)
#1520
0)
#1525
b1101100 4
1)
#1530
0)
#1535
b1101011 4
1)
#1540
0)
#1545
b1101010 4
1)
#1550
0)
#1555
b1101001 4
1)
#1560
0)
#1563
1*
#1565
b1101000 4
1)
#1570
0)
#1575
b1100111 4
1)
#1580
0)
#1585
b1100110 4
1)
#1590
0)
#1595
b1100101 4
1)
#1600
0)
#1605
b1100100 4
1)
#1610
0)
#1615
b1100011 4
1)
#1620
0)
#1625
b1100010 4
1)
#1630
0)
#1635
b1100001 4
1)
#1640
0)
#1645
b1100000 4
1)
#1650
0)
#1655
b1011111 4
1)
#1660
0)
#1665
b1011110 4
1)
#1670
0)
#1675
b1011101 4
1)
#1680
0)
#1685
b1011100 4
1)
#1690
0)
#1695
b1011011 4
1)
#1700
0)
#1705
b1011010 4
1)
#1710
0)
#1715
b1011001 4
1)
#1720
0)
#1725
b1011000 4
1)
#1730
0)
#1735
b1010111 4
1)
#1740
0)
#1745
b1010110 4
1)
#1750
0)
#1755
b1010101 4
1)
#1760
0)
#1765
b1010100 4
1)
#1770
0)
#1775
b1010011 4
1)
#1780
0)
#1785
b1010010 4
1)
#1790
0)
#1795
b1010001 4
1)
#1800
0)
#1805
b1010000 4
1)
#1810
0)
#1815
b1001111 4
1)
#1820
0)
#1825
b1001110 4
1)
#1830
0)
#1835
b1001101 4
1)
#1840
0)
#1845
b1001100 4
1)
#1850
0)
#1855
b1001011 4
1)
#1860
0)
#1865
b1001010 4
1)
#1870
0)
#1875
b1001001 4
1)
#1880
0)
#1885
b1001000 4
1)
#1890
0)
#1895
b1000111 4
1)
#1900
0)
#1905
b1000110 4
1)
#1910
0)
#1915
b1000101 4
1)
#1920
0)
#1925
b1000100 4
1)
#1930
0)
#1935
b1000011 4
1)
#1940
0)
#1945
b1000010 4
1)
#1950
0)
#1955
b1000001 4
1)
#1960
0)
#1965
b1000000 4
1)
#1970
0)
#1975
b111111 4
1)
#1980
0)
#1985
b111110 4
1)
#1990
0)
#1995
b111101 4
1)
#2000
0)
#2005
b111100 4
1)
#2010
0)
#2015
b111011 4
1)
#2020
0)
#2025
b111010 4
1)
#2030
0)
#2035
b111001 4
1)
#2040
0)
#2045
b111000 4
1)
#2050
0)
#2055
b110111 4
1)
#2060
0)
#2065
b110110 4
1)
#2070
0)
#2075
b110101 4
1)
#2080
0)
#2084
18
17
0*
b1000011 ;
1+
#2085
08
07
19
b110100 4
1)
#2090
0)
#2095
b110011 4
1)
#2100
0)
#2105
b110010 4
1)
#2110
0)
#2115
b110001 4
1)
#2120
0)
#2125
b110000 4
1)
#2130
0)
#2135
b101111 4
1)
#2140
0)
#2145
b101110 4
1)
#2150
0)
#2155
b101101 4
1)
#2160
0)
#2165
b101100 4
1)
#2170
0)
#2175
b101011 4
1)
#2180
0)
#2185
b101010 4
1)
#2190
0)
#2195
b101001 4
1)
#2200
0)
#2205
b101000 4
1)
#2210
0)
#2215
b100111 4
1)
#2220
0)
#2225
b100110 4
1)
#2230
0)
#2235
b100101 4
1)
#2240
0)
#2245
b100100 4
1)
#2250
0)
#2255
b100011 4
1)
#2260
0)
#2265
b100010 4
1)
#2270
0)
#2275
b100001 4
1)
#2280
0)
#2285
b100000 4
1)
#2290
0)
#2295
b11111 4
1)
#2300
0)
#2305
b11110 4
1)
#2310
0)
#2315
b11101 4
1)
#2320
0)
#2325
b11100 4
1)
#2330
0)
#2335
b11011 4
1)
#2340
0)
#2345
b11010 4
1)
#2350
0)
#2355
b11001 4
1)
#2360
0)
#2365
b11000 4
1)
#2370
0)
#2375
b10111 4
1)
#2380
0)
#2385
b10110 4
1)
#2390
0)
#2395
b10101 4
1)
#2400
0)
#2405
b10100 4
1)
#2410
0)
#2415
b10011 4
1)
#2420
0)
#2425
b10010 4
1)
#2430
0)
#2435
b10001 4
1)
#2440
0)
#2445
b10000 4
1)
#2450
0)
#2455
b1111 4
1)
#2460
0)
#2465
b1110 4
1)
#2470
0)
#2475
b1101 4
1)
#2480
0)
#2485
b1100 4
1)
#2490
0)
#2495
b1011 4
1)
#2500
0)
#2505
b1010 4
1)
#2510
0)
#2515
b1001 4
1)
#2520
0)
#2525
b1000 4
1)
#2530
0)
#2535
b111 4
1)
#2540
0)
#2545
b110 4
1)
#2550
0)
#2555
b101 4
1)
#2560
0)
#2565
b100 4
1)
#2570
0)
#2575
b11 4
1)
#2580
0)
#2585
b10 4
1)
#2590
0)
#2595
b1 4
1)
#2600
0)
#2605
10
b0 4
1)
1*
#2610
0)
#2615
b10000000 '
b10000000 ,
b10000000 6
b10 (
b10 -
b10 5
00
b1101000 4
1)
#2620
0)
#2625
b1100111 4
1)
#2630
0)
#2635
b1100110 4
1)
#2640
0)
#2645
b1100101 4
1)
#2650
0)
#2655
b1100100 4
1)
#2660
0)
#2665
b1100011 4
1)
#2670
0)
#2675
b1100010 4
1)
#2680
0)
#2685
b1100001 4
1)
#2690
0)
#2695
b1100000 4
1)
#2700
0)
#2705
b1011111 4
1)
#2710
0)
#2715
b1011110 4
1)
#2720
0)
#2725
b1011101 4
1)
#2730
0)
#2735
b1011100 4
1)
#2740
0)
#2745
b1011011 4
1)
#2750
0)
#2755
b1011010 4
1)
#2760
0)
#2765
b1011001 4
1)
#2770
0)
#2775
b1011000 4
1)
#2780
0)
#2785
b1010111 4
1)
#2790
0)
#2795
b1010110 4
1)
#2800
0)
#2805
b1010101 4
1)
#2810
0)
#2815
b1010100 4
1)
#2820
0)
#2825
b1010011 4
1)
#2830
0)
#2835
b1010010 4
1)
#2840
0)
#2845
b1010001 4
1)
#2850
0)
#2855
b1010000 4
1)
#2860
0)
#2865
b1001111 4
1)
#2870
0)
#2875
b1001110 4
1)
#2880
0)
#2885
b1001101 4
1)
#2890
0)
#2895
b1001100 4
1)
#2900
0)
#2905
b1001011 4
1)
#2910
0)
#2915
b1001010 4
1)
#2920
0)
#2925
b1001001 4
1)
#2930
0)
#2935
b1001000 4
1)
#2940
0)
#2945
b1000111 4
1)
#2950
0)
#2955
b1000110 4
1)
#2960
0)
#2965
b1000101 4
1)
#2970
0)
#2975
b1000100 4
1)
#2980
0)
#2985
b1000011 4
1)
#2990
0)
#2995
b1000010 4
1)
#3000
0)
#3005
b1000001 4
1)
#3010
0)
#3015
b1000000 4
1)
#3020
0)
#3025
b111111 4
1)
#3030
0)
#3035
b111110 4
1)
#3040
0)
#3045
b111101 4
1)
#3050
0)
#3055
b111100 4
1)
#3060
0)
#3065
b111011 4
1)
#3070
0)
#3075
b111010 4
1)
#3080
0)
#3085
b111001 4
1)
#3090
0)
#3095
b111000 4
1)
#3100
0)
#3105
b110111 4
1)
#3110
0)
#3115
b110110 4
1)
#3120
0)
#3125
b110101 4
1)
#3126
0*
b1000010 ;
#3130
0)
#3135
b110100 4
1)
#3140
0)
#3145
b110011 4
1)
#3150
0)
#3155
b110010 4
1)
#3160
0)
#3165
b110001 4
1)
#3170
0)
#3175
b110000 4
1)
#3180
0)
#3185
b101111 4
1)
#3190
0)
#3195
b101110 4
1)
#3200
0)
#3205
b101101 4
1)
#3210
0)
#3215
b101100 4
1)
#3220
0)
#3225
b101011 4
1)
#3230
0)
#3235
b101010 4
1)
#3240
0)
#3245
b101001 4
1)
#3250
0)
#3255
b101000 4
1)
#3260
0)
#3265
b100111 4
1)
#3270
0)
#3275
b100110 4
1)
#3280
0)
#3285
b100101 4
1)
#3290
0)
#3295
b100100 4
1)
#3300
0)
#3305
b100011 4
1)
#3310
0)
#3315
b100010 4
1)
#3320
0)
#3325
b100001 4
1)
#3330
0)
#3335
b100000 4
1)
#3340
0)
#3345
b11111 4
1)
#3350
0)
#3355
b11110 4
1)
#3360
0)
#3365
b11101 4
1)
#3370
0)
#3375
b11100 4
1)
#3380
0)
#3385
b11011 4
1)
#3390
0)
#3395
b11010 4
1)
#3400
0)
#3405
b11001 4
1)
#3410
0)
#3415
b11000 4
1)
#3420
0)
#3425
b10111 4
1)
#3430
0)
#3435
b10110 4
1)
#3440
0)
#3445
b10101 4
1)
#3450
0)
#3455
b10100 4
1)
#3460
0)
#3465
b10011 4
1)
#3470
0)
#3475
b10010 4
1)
#3480
0)
#3485
b10001 4
1)
#3490
0)
#3495
b10000 4
1)
#3500
0)
#3505
b1111 4
1)
#3510
0)
#3515
b1110 4
1)
#3520
0)
#3525
b1101 4
1)
#3530
0)
#3535
b1100 4
1)
#3540
0)
#3545
b1011 4
1)
#3550
0)
#3555
b1010 4
1)
#3560
0)
#3565
b1001 4
1)
#3570
0)
#3575
b1000 4
1)
#3580
0)
#3585
b111 4
1)
#3590
0)
#3595
b110 4
1)
#3600
0)
#3605
b101 4
1)
#3610
0)
#3615
b100 4
1)
#3620
0)
#3625
b11 4
1)
#3630
0)
#3635
b10 4
1)
#3640
0)
#3645
b1 4
1)
#3647
1*
#3650
0)
#3655
10
b0 4
1)
#3660
0)
#3665
b11000000 '
b11000000 ,
b11000000 6
b110 3
00
b1101000 4
1)
#3670
0)
#3675
b1100111 4
1)
#3680
0)
#3685
b1100110 4
1)
#3690
0)
#3695
b1100101 4
1)
#3700
0)
#3705
b1100100 4
1)
#3710
0)
#3715
b1100011 4
1)
#3720
0)
#3725
b1100010 4
1)
#3730
0)
#3735
b1100001 4
1)
#3740
0)
#3745
b1100000 4
1)
#3750
0)
#3755
b1011111 4
1)
#3760
0)
#3765
b1011110 4
1)
#3770
0)
#3775
b1011101 4
1)
#3780
0)
#3785
b1011100 4
1)
#3790
0)
#3795
b1011011 4
1)
#3800
0)
#3805
b1011010 4
1)
#3810
0)
#3815
b1011001 4
1)
#3820
0)
#3825
b1011000 4
1)
#3830
0)
#3835
b1010111 4
1)
#3840
0)
#3845
b1010110 4
1)
#3850
0)
#3855
b1010101 4
1)
#3860
0)
#3865
b1010100 4
1)
#3870
0)
#3875
b1010011 4
1)
#3880
0)
#3885
b1010010 4
1)
#3890
0)
#3895
b1010001 4
1)
#3900
0)
#3905
b1010000 4
1)
#3910
0)
#3915
b1001111 4
1)
#3920
0)
#3925
b1001110 4
1)
#3930
0)
#3935
b1001101 4
1)
#3940
0)
#3945
b1001100 4
1)
#3950
0)
#3955
b1001011 4
1)
#3960
0)
#3965
b1001010 4
1)
#3970
0)
#3975
b1001001 4
1)
#3980
0)
#3985
b1001000 4
1)
#3990
0)
#3995
b1000111 4
1)
#4000
0)
#4005
b1000110 4
1)
#4010
0)
#4015
b1000101 4
1)
#4020
0)
#4025
b1000100 4
1)
#4030
0)
#4035
b1000011 4
1)
#4040
0)
#4045
b1000010 4
1)
#4050
0)
#4055
b1000001 4
1)
#4060
0)
#4065
b1000000 4
1)
#4070
0)
#4075
b111111 4
1)
#4080
0)
#4085
b111110 4
1)
#4090
0)
#4095
b111101 4
1)
#4100
0)
#4105
b111100 4
1)
#4110
0)
#4115
b111011 4
1)
#4120
0)
#4125
b111010 4
1)
#4130
0)
#4135
b111001 4
1)
#4140
0)
#4145
b111000 4
1)
#4150
0)
#4155
b110111 4
1)
#4160
0)
#4165
b110110 4
1)
#4168
0*
b1000001 ;
#4170
0)
#4175
b110101 4
1)
#4180
0)
#4185
b110100 4
1)
#4190
0)
#4195
b110011 4
1)
#4200
0)
#4205
b110010 4
1)
#4210
0)
#4215
b110001 4
1)
#4220
0)
#4225
b110000 4
1)
#4230
0)
#4235
b101111 4
1)
#4240
0)
#4245
b101110 4
1)
#4250
0)
#4255
b101101 4
1)
#4260
0)
#4265
b101100 4
1)
#4270
0)
#4275
b101011 4
1)
#4280
0)
#4285
b101010 4
1)
#4290
0)
#4295
b101001 4
1)
#4300
0)
#4305
b101000 4
1)
#4310
0)
#4315
b100111 4
1)
#4320
0)
#4325
b100110 4
1)
#4330
0)
#4335
b100101 4
1)
#4340
0)
#4345
b100100 4
1)
#4350
0)
#4355
b100011 4
1)
#4360
0)
#4365
b100010 4
1)
#4370
0)
#4375
b100001 4
1)
#4380
0)
#4385
b100000 4
1)
#4390
0)
#4395
b11111 4
1)
#4400
0)
#4405
b11110 4
1)
#4410
0)
#4415
b11101 4
1)
#4420
0)
#4425
b11100 4
1)
#4430
0)
#4435
b11011 4
1)
#4440
0)
#4445
b11010 4
1)
#4450
0)
#4455
b11001 4
1)
#4460
0)
#4465
b11000 4
1)
#4470
0)
#4475
b10111 4
1)
#4480
0)
#4485
b10110 4
1)
#4490
0)
#4495
b10101 4
1)
#4500
0)
#4505
b10100 4
1)
#4510
0)
#4515
b10011 4
1)
#4520
0)
#4525
b10010 4
1)
#4530
0)
#4535
b10001 4
1)
#4540
0)
#4545
b10000 4
1)
#4550
0)
#4555
b1111 4
1)
#4560
0)
#4565
b1110 4
1)
#4570
0)
#4575
b1101 4
1)
#4580
0)
#4585
b1100 4
1)
#4590
0)
#4595
b1011 4
1)
#4600
0)
#4605
b1010 4
1)
#4610
0)
#4615
b1001 4
1)
#4620
0)
#4625
b1000 4
1)
#4630
0)
#4635
b111 4
1)
#4640
0)
#4645
b110 4
1)
#4650
0)
#4655
b101 4
1)
#4660
0)
#4665
b100 4
1)
#4670
0)
#4675
b11 4
1)
#4680
0)
#4685
b10 4
1)
#4689
1*
#4690
0)
#4695
b1 4
1)
#4700
0)
#4705
10
b0 4
1)
#4710
0)
#4715
b11100000 '
b11100000 ,
b11100000 6
b101 3
00
b1101000 4
1)
#4720
0)
#4725
b1100111 4
1)
#4730
0)
#4735
b1100110 4
1)
#4740
0)
#4745
b1100101 4
1)
#4750
0)
#4755
b1100100 4
1)
#4760
0)
#4765
b1100011 4
1)
#4770
0)
#4775
b1100010 4
1)
#4780
0)
#4785
b1100001 4
1)
#4790
0)
#4795
b1100000 4
1)
#4800
0)
#4805
b1011111 4
1)
#4810
0)
#4815
b1011110 4
1)
#4820
0)
#4825
b1011101 4
1)
#4830
0)
#4835
b1011100 4
1)
#4840
0)
#4845
b1011011 4
1)
#4850
0)
#4855
b1011010 4
1)
#4860
0)
#4865
b1011001 4
1)
#4870
0)
#4875
b1011000 4
1)
#4880
0)
#4885
b1010111 4
1)
#4890
0)
#4895
b1010110 4
1)
#4900
0)
#4905
b1010101 4
1)
#4910
0)
#4915
b1010100 4
1)
#4920
0)
#4925
b1010011 4
1)
#4930
0)
#4935
b1010010 4
1)
#4940
0)
#4945
b1010001 4
1)
#4950
0)
#4955
b1010000 4
1)
#4960
0)
#4965
b1001111 4
1)
#4970
0)
#4975
b1001110 4
1)
#4980
0)
#4985
b1001101 4
1)
#4990
0)
#4995
b1001100 4
1)
#5000
0)
#5005
b1001011 4
1)
#5010
0)
#5015
b1001010 4
1)
#5020
0)
#5025
b1001001 4
1)
#5030
0)
#5035
b1001000 4
1)
#5040
0)
#5045
b1000111 4
1)
#5050
0)
#5055
b1000110 4
1)
#5060
0)
#5065
b1000101 4
1)
#5070
0)
#5075
b1000100 4
1)
#5080
0)
#5085
b1000011 4
1)
#5090
0)
#5095
b1000010 4
1)
#5100
0)
#5105
b1000001 4
1)
#5110
0)
#5115
b1000000 4
1)
#5120
0)
#5125
b111111 4
1)
#5130
0)
#5135
b111110 4
1)
#5140
0)
#5145
b111101 4
1)
#5150
0)
#5155
b111100 4
1)
#5160
0)
#5165
b111011 4
1)
#5170
0)
#5175
b111010 4
1)
#5180
0)
#5185
b111001 4
1)
#5190
0)
#5195
b111000 4
1)
#5200
0)
#5205
b110111 4
1)
#5210
1.
1/
17
0)
0*
b1000000 ;
0+
#5215
07
0.
0/
b110110 4
09
1)
#5220
0)
#5225
b110101 4
1)
#5230
0)
#5235
b110100 4
1)
#5240
0)
#5245
b110011 4
1)
#5250
0)
#5255
b110010 4
1)
#5260
0)
#5265
b110001 4
1)
#5270
0)
#5275
b110000 4
1)
#5280
0)
#5285
b101111 4
1)
#5290
0)
#5295
b101110 4
1)
#5300
0)
#5305
b101101 4
1)
#5310
0)
#5315
b101100 4
1)
#5320
0)
#5325
b101011 4
1)
#5330
0)
#5335
b101010 4
1)
#5340
0)
#5345
b101001 4
1)
#5350
0)
#5355
b101000 4
1)
#5360
0)
#5365
b100111 4
1)
#5370
0)
#5375
b100110 4
1)
#5380
0)
#5385
b100101 4
1)
#5390
0)
#5395
b100100 4
1)
#5400
0)
#5405
b100011 4
1)
#5410
0)
#5415
b100010 4
1)
#5420
0)
#5425
b100001 4
1)
#5430
0)
#5435
b100000 4
1)
#5440
0)
#5445
b11111 4
1)
#5450
0)
#5455
b11110 4
1)
#5460
0)
#5465
b11101 4
1)
#5470
0)
#5475
b11100 4
1)
#5480
0)
#5485
b11011 4
1)
#5490
0)
#5495
b11010 4
1)
#5500
0)
#5505
b11001 4
1)
#5510
0)
#5515
b11000 4
1)
#5520
0)
#5525
b10111 4
1)
#5530
0)
#5535
b10110 4
1)
#5540
0)
#5545
b10101 4
1)
#5550
0)
#5555
b10100 4
1)
#5560
0)
#5565
b10011 4
1)
#5570
0)
#5575
b10010 4
1)
#5580
0)
#5585
b10001 4
1)
#5590
0)
#5595
b10000 4
1)
#5600
0)
#5605
b1111 4
1)
#5610
0)
#5615
b1110 4
1)
#5620
0)
#5625
b1101 4
1)
#5630
0)
#5635
b1100 4
1)
#5640
0)
