common.sv
`include "./dist/uart.sv"
`include "./dist/ref_gen.sv"
`include "./dist/pred.sv"
`include "./dist/selector.sv"
`include "./dist/interrupter.sv"

/*
real uart frequency is 9600 Hz
assume 960 kHz for faster simulation
*/

localparam 	GEN_CLK_FREQ = 100_000_000,
						TB_CLK_FREQ = 1_000_000_000,
						UART_FREQ = 960_000,

						FRAME_FREQ = 2 * UART_FREQ,
						FRAME = `div(GEN_CLK_FREQ, FRAME_FREQ),
						FRAME_TB = `div(TB_CLK_FREQ, FRAME_FREQ),
						CLK_FRAME_TB = `div(TB_CLK_FREQ, (2 * GEN_CLK_FREQ)),

						CONF_PAR_MAX = 255,
						FRAME_CNT_MAX_1 = 3 * FRAME,
						FRAME_CNT_MAX_2 = 2 * FRAME,
						DATA_BIT_CNT_MAX = 7;

modules/defines.sv
/*
calculates bus width from its max value
`width(255) -> 8
*/
`define width(val) $clog2(val+1)


`define reg(val) reg[$clog2(val+1)-1:0]

`define wire(val) wire[$clog2(val+1)-1:0]

/*
defines 2d array reg
`reg_2d(my_array, 255, 4) -> reg[8] my_array [4:0]
*/
`define reg_2d(name, width_val, length_val) reg[$clog2(width_val+1)-1:0] \
 ``name`` [length_val:0]

/*
defines 2d array wire
`wire_2d(my_array, 255, 4) -> wire[8] my_array [4:0]
*/
`define wire_2d(name, width_val, length_val) wire[$clog2(width_val+1)-1:0] \
 ``name`` [length_val:0]

`define div(A, B) A / B + (2*(A % B) >= B ? 1 : 0)

`define lookup \
8'd1: cnt <= 14'd9999; \
8'd2: cnt <= 14'd4999; \
8'd3: cnt <= 14'd3332; \
8'd4: cnt <= 14'd2499; \
8'd5: cnt <= 14'd1999; \
8'd6: cnt <= 14'd1666; \
8'd7: cnt <= 14'd1428; \
8'd8: cnt <= 14'd1249; \
8'd9: cnt <= 14'd1110; \
8'd10: cnt <= 14'd999; \
8'd11: cnt <= 14'd908; \
8'd12: cnt <= 14'd832; \
8'd13: cnt <= 14'd768; \
8'd14: cnt <= 14'd713; \
8'd15: cnt <= 14'd666; \
8'd16: cnt <= 14'd624; \
8'd17: cnt <= 14'd587; \
8'd18: cnt <= 14'd555; \
8'd19: cnt <= 14'd525; \
8'd20: cnt <= 14'd499; \
8'd21: cnt <= 14'd475; \
8'd22: cnt <= 14'd454; \
8'd23: cnt <= 14'd434; \
8'd24: cnt <= 14'd416; \
8'd25: cnt <= 14'd399; \
8'd26: cnt <= 14'd384; \
8'd27: cnt <= 14'd369; \
8'd28: cnt <= 14'd356; \
8'd29: cnt <= 14'd344; \
8'd30: cnt <= 14'd332; \
8'd31: cnt <= 14'd322; \
8'd32: cnt <= 14'd312; \
8'd33: cnt <= 14'd302; \
8'd34: cnt <= 14'd293; \
8'd35: cnt <= 14'd285; \
8'd36: cnt <= 14'd277; \
8'd37: cnt <= 14'd269; \
8'd38: cnt <= 14'd262; \
8'd39: cnt <= 14'd255; \
8'd40: cnt <= 14'd249; \
8'd41: cnt <= 14'd243; \
8'd42: cnt <= 14'd237; \
8'd43: cnt <= 14'd232; \
8'd44: cnt <= 14'd226; \
8'd45: cnt <= 14'd221; \
8'd46: cnt <= 14'd216; \
8'd47: cnt <= 14'd212; \
8'd48: cnt <= 14'd207; \
8'd49: cnt <= 14'd203; \
8'd50: cnt <= 14'd199; \
8'd51: cnt <= 14'd195; \
8'd52: cnt <= 14'd191; \
8'd53: cnt <= 14'd188; \
8'd54: cnt <= 14'd184; \
8'd55: cnt <= 14'd181; \
8'd56: cnt <= 14'd178; \
8'd57: cnt <= 14'd174; \
8'd58: cnt <= 14'd171; \
8'd59: cnt <= 14'd168; \
8'd60: cnt <= 14'd166; \
8'd61: cnt <= 14'd163; \
8'd62: cnt <= 14'd160; \
8'd63: cnt <= 14'd158; \
8'd64: cnt <= 14'd155; \
8'd65: cnt <= 14'd153; \
8'd66: cnt <= 14'd151; \
8'd67: cnt <= 14'd148; \
8'd68: cnt <= 14'd146; \
8'd69: cnt <= 14'd144; \
8'd70: cnt <= 14'd142; \
8'd71: cnt <= 14'd140; \
8'd72: cnt <= 14'd138; \
8'd73: cnt <= 14'd136; \
8'd74: cnt <= 14'd134; \
8'd75: cnt <= 14'd132; \
8'd76: cnt <= 14'd131; \
8'd77: cnt <= 14'd129; \
8'd78: cnt <= 14'd127; \
8'd79: cnt <= 14'd126; \
8'd80: cnt <= 14'd124; \
8'd81: cnt <= 14'd122; \
8'd82: cnt <= 14'd121; \
8'd83: cnt <= 14'd119; \
8'd84: cnt <= 14'd118; \
8'd85: cnt <= 14'd117; \
8'd86: cnt <= 14'd115; \
8'd87: cnt <= 14'd114; \
8'd88: cnt <= 14'd113; \
8'd89: cnt <= 14'd111; \
8'd90: cnt <= 14'd110; \
8'd91: cnt <= 14'd109; \
8'd92: cnt <= 14'd108; \
8'd93: cnt <= 14'd107; \
8'd94: cnt <= 14'd105; \
8'd95: cnt <= 14'd104; \
8'd96: cnt <= 14'd103; \
8'd97: cnt <= 14'd102; \
8'd98: cnt <= 14'd101; \
8'd99: cnt <= 14'd100; \
8'd100: cnt <= 14'd99; \
8'd101: cnt <= 14'd98; \
8'd102: cnt <= 14'd97; \
8'd103: cnt <= 14'd96; \
8'd104: cnt <= 14'd95; \
8'd105: cnt <= 14'd94; \
8'd106: cnt <= 14'd93; \
8'd107: cnt <= 14'd92; \
8'd108: cnt <= 14'd92; \
8'd109: cnt <= 14'd91; \
8'd110: cnt <= 14'd90; \
8'd111: cnt <= 14'd89; \
8'd112: cnt <= 14'd88; \
8'd113: cnt <= 14'd87; \
8'd114: cnt <= 14'd87; \
8'd115: cnt <= 14'd86; \
8'd116: cnt <= 14'd85; \
8'd117: cnt <= 14'd84; \
8'd118: cnt <= 14'd84; \
8'd119: cnt <= 14'd83; \
8'd120: cnt <= 14'd82; \
8'd121: cnt <= 14'd82; \
8'd122: cnt <= 14'd81; \
8'd123: cnt <= 14'd80; \
8'd124: cnt <= 14'd80; \
8'd125: cnt <= 14'd79; \
8'd126: cnt <= 14'd78; \
8'd127: cnt <= 14'd78; \
8'd128: cnt <= 14'd77; \
8'd129: cnt <= 14'd77; \
8'd130: cnt <= 14'd76; \
8'd131: cnt <= 14'd75; \
8'd132: cnt <= 14'd75; \
8'd133: cnt <= 14'd74; \
8'd134: cnt <= 14'd74; \
8'd135: cnt <= 14'd73; \
8'd136: cnt <= 14'd73; \
8'd137: cnt <= 14'd72; \
8'd138: cnt <= 14'd71; \
8'd139: cnt <= 14'd71; \
8'd140: cnt <= 14'd70; \
8'd141: cnt <= 14'd70; \
8'd142: cnt <= 14'd69; \
8'd143: cnt <= 14'd69; \
8'd144: cnt <= 14'd68; \
8'd145: cnt <= 14'd68; \
8'd146: cnt <= 14'd67; \
8'd147: cnt <= 14'd67; \
8'd148: cnt <= 14'd67; \
8'd149: cnt <= 14'd66; \
8'd150: cnt <= 14'd66; \
8'd151: cnt <= 14'd65; \
8'd152: cnt <= 14'd65; \
8'd153: cnt <= 14'd64; \
8'd154: cnt <= 14'd64; \
8'd155: cnt <= 14'd64; \
8'd156: cnt <= 14'd63; \
8'd157: cnt <= 14'd63; \
8'd158: cnt <= 14'd62; \
8'd159: cnt <= 14'd62; \
8'd160: cnt <= 14'd62; \
8'd161: cnt <= 14'd61; \
8'd162: cnt <= 14'd61; \
8'd163: cnt <= 14'd60; \
8'd164: cnt <= 14'd60; \
8'd165: cnt <= 14'd60; \
8'd166: cnt <= 14'd59; \
8'd167: cnt <= 14'd59; \
8'd168: cnt <= 14'd59; \
8'd169: cnt <= 14'd58; \
8'd170: cnt <= 14'd58; \
8'd171: cnt <= 14'd57; \
8'd172: cnt <= 14'd57; \
8'd173: cnt <= 14'd57; \
8'd174: cnt <= 14'd56; \
8'd175: cnt <= 14'd56; \
8'd176: cnt <= 14'd56; \
8'd177: cnt <= 14'd55; \
8'd178: cnt <= 14'd55; \
8'd179: cnt <= 14'd55; \
8'd180: cnt <= 14'd55; \
8'd181: cnt <= 14'd54; \
8'd182: cnt <= 14'd54; \
8'd183: cnt <= 14'd54; \
8'd184: cnt <= 14'd53; \
8'd185: cnt <= 14'd53; \
8'd186: cnt <= 14'd53; \
8'd187: cnt <= 14'd52; \
8'd188: cnt <= 14'd52; \
8'd189: cnt <= 14'd52; \
8'd190: cnt <= 14'd52; \
8'd191: cnt <= 14'd51; \
8'd192: cnt <= 14'd51; \
8'd193: cnt <= 14'd51; \
8'd194: cnt <= 14'd51; \
8'd195: cnt <= 14'd50; \
8'd196: cnt <= 14'd50; \
8'd197: cnt <= 14'd50; \
8'd198: cnt <= 14'd50; \
8'd199: cnt <= 14'd49; \
8'd200: cnt <= 14'd49; \
8'd201: cnt <= 14'd49; \
8'd202: cnt <= 14'd49; \
8'd203: cnt <= 14'd48; \
8'd204: cnt <= 14'd48; \
8'd205: cnt <= 14'd48; \
8'd206: cnt <= 14'd48; \
8'd207: cnt <= 14'd47; \
8'd208: cnt <= 14'd47; \
8'd209: cnt <= 14'd47; \
8'd210: cnt <= 14'd47; \
8'd211: cnt <= 14'd46; \
8'd212: cnt <= 14'd46; \
8'd213: cnt <= 14'd46; \
8'd214: cnt <= 14'd46; \
8'd215: cnt <= 14'd46; \
8'd216: cnt <= 14'd45; \
8'd217: cnt <= 14'd45; \
8'd218: cnt <= 14'd45; \
8'd219: cnt <= 14'd45; \
8'd220: cnt <= 14'd44; \
8'd221: cnt <= 14'd44; \
8'd222: cnt <= 14'd44; \
8'd223: cnt <= 14'd44; \
8'd224: cnt <= 14'd44; \
8'd225: cnt <= 14'd43; \
8'd226: cnt <= 14'd43; \
8'd227: cnt <= 14'd43; \
8'd228: cnt <= 14'd43; \
8'd229: cnt <= 14'd43; \
8'd230: cnt <= 14'd42; \
8'd231: cnt <= 14'd42; \
8'd232: cnt <= 14'd42; \
8'd233: cnt <= 14'd42; \
8'd234: cnt <= 14'd42; \
8'd235: cnt <= 14'd42; \
8'd236: cnt <= 14'd41; \
8'd237: cnt <= 14'd41; \
8'd238: cnt <= 14'd41; \
8'd239: cnt <= 14'd41; \
8'd240: cnt <= 14'd41; \
8'd241: cnt <= 14'd40; \
8'd242: cnt <= 14'd40; \
8'd243: cnt <= 14'd40; \
8'd244: cnt <= 14'd40; \
8'd245: cnt <= 14'd40; \
8'd246: cnt <= 14'd40; \
8'd247: cnt <= 14'd39; \
8'd248: cnt <= 14'd39; \
8'd249: cnt <= 14'd39; \
8'd250: cnt <= 14'd39; \
8'd251: cnt <= 14'd39; \
8'd252: cnt <= 14'd39; \
8'd253: cnt <= 14'd39; \
8'd254: cnt <= 14'd38; \
8'd255: cnt <= 14'd38;

dist/interrupter.sv
`include "./modules/defines.sv"
module int_gen_160486547415602987277149564336 #(parameter
			 CLK_MHZ = 100,
			 PAR_MAX_VAL = 255
																							 )
			 (
				 input wire clk,
				 input `wire(PAR_MAX_VAL) freq_par,
				 input `wire(PAR_MAX_VAL) pw_par,
				 output wire out
			 );

localparam k = 100;

`reg(100 * CLK_MHZ) cnt = 0; // 500_000

always @(posedge clk) begin
	if (cnt) cnt <= cnt - 1;
	else begin
		case(freq_par)
			`lookup
		endcase
	end
end

assign out = cnt < k * pw_par;

endmodule

	module edge_det_160486547415602987277149564336
	(
		input wire clk,
		input wire sgn,
		output wire out_p,
		output wire out_n,
		output wire out
	);

reg sgn_pre = 0;

assign out_p = sgn && ~sgn_pre,
			 out_n = ~sgn && sgn_pre,
			 out = sgn ^ sgn_pre;

always @(posedge clk)
	if (out) sgn_pre <= sgn;

endmodule



	module sync_160486547415602987277149564336 #(parameter
			WIDTH = 1
																							)
	(
		input wire clk,
		input wire[WIDTH-1:0] data_raw,
		output reg[WIDTH-1:0] data = 0
	);

reg[WIDTH-1:0] internal = 0;

always @(posedge clk)
	{ data, internal } <= { internal, data_raw };

endmodule


	module interrupter (
		input wire clk,
		input wire gen,
		output wire out
	);

reg ff = 0;

int_gen_160486547415602987277149564336 i(
																				 .clk(clk),
																				 .freq_par(8'd4),	// 100 -> 1 MHz -> 1us
																				 .pw_par(8'd13),
																				 .out(int_wire)
																			 );

edge_det_160486547415602987277149564336 gen_p(.clk(clk), .sgn(gen), .out_p(gen_edge_p));

sync_160486547415602987277149564336 gen_d(
																			.clk(clk),
																			.data_raw(gen),
																			.data(gen_del)
																		);

always @(posedge clk) if (gen_edge_p) ff <= !int_wire;

assign out = ff && gen_del;

endmodule

dist/selector.sv
`include "./modules/defines.sv"
module edge_det_160486547416609495228937060538
			 (
				 input wire clk,
				 input wire sgn,
				 output wire out_p,
				 output wire out_n,
				 output wire out
			 );

reg sgn_pre = 0;

assign out_p = sgn && ~sgn_pre,
			 out_n = ~sgn && sgn_pre,
			 out = sgn ^ sgn_pre;

always @(posedge clk)
	if (out) sgn_pre <= sgn;

endmodule


	module selector #(parameter
										CLK_MHZ = 100,
										PERIODS_TO_SWITCH = 4,
										RESET_TIMEOUT_US = 4
									 )
	(
		input wire clk,
		input wire gen,
		input wire fb,
		output wire out
	);

typedef enum { STATE_0, STATE_1 } State;

localparam TIMEOUT_CNT_MAX = CLK_MHZ * PERIODS_TO_SWITCH;

`reg(TIMEOUT_CNT_MAX) timeout_cnt = TIMEOUT_CNT_MAX - 1;
`reg(PERIODS_TO_SWITCH) per_to_sw_cnt = PERIODS_TO_SWITCH;
`reg(STATE_1) state = STATE_0;

edge_det_160486547416609495228937060538 edge_det_gen(.clk(clk), .sgn(gen), .out_n(gen_edge_n));
edge_det_160486547416609495228937060538 edge_det_fb(.clk(clk), .sgn(fb), .out_n(fb_edge_n));

// state transition conditions
wire cond_1 = !per_to_sw_cnt && fb_edge_n,	// some gen periods passed
		 cond_0 = !timeout_cnt && !gen;	// no signal on fb input

always @(posedge clk) begin
	// state values
	case(state)
		STATE_0: if (gen_edge_n) per_to_sw_cnt <= per_to_sw_cnt ? per_to_sw_cnt - 1 : PERIODS_TO_SWITCH;
		STATE_1: if (fb) timeout_cnt <= TIMEOUT_CNT_MAX - 1;
			else if (timeout_cnt) timeout_cnt <= timeout_cnt - 1;
	endcase

	// state transitions
	case(state)
		STATE_0: if (cond_1) state <= STATE_1;
		STATE_1: if (cond_0) begin
				state <= STATE_0;
				timeout_cnt <= TIMEOUT_CNT_MAX - 1;
			end
	endcase
end

assign out = state == STATE_0 ? gen : fb;

endmodule

dist/sync.sv
`include "./modules/defines.sv"

module sync #(parameter
							WIDTH = 1
						 )
			 (
				 input wire clk,
				 input wire[WIDTH-1:0] data_raw,
				 output reg[WIDTH-1:0] data = 0
			 );

reg[WIDTH-1:0] internal = 0;

always @(posedge clk)
	{ data, internal } <= { internal, data_raw };

endmodule

src/pred.sv
`include "./modules/defines.sv"
`include "./modules/sync.sv"

module pred #(parameter
							PRED_PARAMETER = 255
						 )
			 (
				 input wire clk,
				 input wire sgn,
				 input `wire(PRED_PARAMETER) shift,
				 output reg sgn_pre = 0
			 );

// cdc synchronizer
sync #(.WIDTH(1))
		 s1(
			 .clk(clk),
			 .data_raw(sgn),
			 .data(sgn_s)
		 );

`reg(PRED_PARAMETER) cnt;
initial cnt = shift;

always @(posedge clk) begin
	if (sgn_s ^ sgn_pre) begin
		if (cnt) cnt <= cnt - 1;
		else begin
			cnt <= shift - 1;
			sgn_pre <= sgn_s;
		end
	end
end

endmodule

dist/ref_gen.sv
`include "./modules/defines.sv"

module ref_gen #(parameter
								 CLK_MHZ = 100,
								 FREQ_KHZ_MIN = 100,	// actual range from 200 to 400
								 FREQ_KHZ_MAX = 400,
								 GEN_PARAMETER = 255
								)
			 (
				 input wire clk,
				 input `wire(GEN_PARAMETER) inp,
				 output reg out = 0
			 );

localparam CNT_MIN = `div(500 * CLK_MHZ, FREQ_KHZ_MAX),
					 CNT_MAX = `div(500 * CLK_MHZ, FREQ_KHZ_MIN);

`reg(GEN_PARAMETER) gen_param;
initial gen_param = inp;

`reg(CNT_MAX) cnt = 0;

always @(posedge clk) begin
	if (cnt) cnt <= cnt - 1;
	else begin
		cnt <= CNT_MIN - 1 + gen_param;
		out <= ~out;
	end
end

endmodule

entry.sv
`include "common.sv"

// 9600 Hz uart module uses 54 LE


module entry (
				 input wire clk,
				 input wire uart_data,
				 output `wire_2d(sh_reg, CONF_PAR_MAX, CONF_PAR_4),
				 //output wire[7:0] storage,
				 //output wire[1:0] state

				 output wire gen_out,

				 input wire fb_in,
				 output wire fb_out,

				 output wire sel_out,

				 output wire int_out
			 );

ref_gen rg1(
					.clk(clk),
					.inp(8'd0),
					.out(gen_out)
				);

pred p1(
			 .clk(clk),
			 .sgn(fb_in),
			 .shift(8'd30),
			 .sgn_pre(fb_out)
		 );

selector s1(
					 .clk(clk),
					 .gen(gen_out),
					 .fb(fb_out),
					 .out(sel_out)
				 );

interrupter i1(
							.clk(clk),
							.gen(sel_out),
							.out(int_out)
						);



/*
uart #(
			 .CONF_PAR_MAX(CONF_PAR_MAX),
			 .FRAME_CNT_MAX_1(FRAME_CNT_MAX_1),
			 .FRAME_CNT_MAX_2(FRAME_CNT_MAX_2),
			 .DATA_BIT_CNT_MAX(DATA_BIT_CNT_MAX)
		 ) uart_ins(
			 .clk(clk),
			 .uart_data(uart_data),
			 .sh_reg(sh_reg)
			 //.storage(storage),
			 //.state(state)
		 );
*/

endmodule

tb.sv
`timescale 1ns/1ns
`include "entry.sv"

module test_entry;

reg clk_tb, uart_data_tb, uart_clk_tb;
wire is_data_ready_tb, out_tb;
`wire_2d(sh_reg_tb, CONF_PAR_MAX, CONF_PAR_4);
`wire(CONF_PAR_MAX) sh_0, sh_1, sh_2, sh_3, sh_4;
//wire[7:0] storage_tb;
//wire[1:0] state_tb;
wire gen_out_tb, fb_in_tb, fb_out_tb, sel_out_tb, int_out_tb;
reg fb_tb = 0, fb_mask = 1;

assign sh_0 = sh_reg_tb[0],
			 sh_1 = sh_reg_tb[1],
			 sh_2 = sh_reg_tb[2],
			 sh_3 = sh_reg_tb[3],
			 sh_4 = sh_reg_tb[4],

			 fb_in_tb = fb_tb && fb_mask;


entry entry_inst(
				.clk(clk_tb),
				.uart_data(uart_data_tb),
				.sh_reg(sh_reg_tb),
				//.storage(storage_tb),
				//.state(state_tb)

				.gen_out(gen_out_tb),

				.fb_in(fb_in_tb),
				.fb_out(fb_out_tb),

				.sel_out(sel_out_tb),

				.int_out(int_out_tb)
			);

localparam //test_data = 49'b0_00101100_10_01001100_10_00101100_10_01001100_10_00101100, // 42424
					 test_data = 69'b0_11101100_10_01001100_10_00101100_10_01001100_10_00101100_10_00101100_10_10101100, // 72424_45
					 packet_size = $bits(test_data);

// clk
always #CLK_FRAME_TB clk_tb = ~clk_tb;
always #FRAME_TB uart_clk_tb = ~uart_clk_tb;

initial #(2 * (packet_size + 2) * FRAME_TB) $finish;

initial begin
	clk_tb = 0;
	uart_data_tb = 1;
	uart_clk_tb = 0;

	for (int i = packet_size; i > 0; i--) begin
		#(2 * FRAME_TB) uart_data_tb = test_data[i-1];
		if (i == 1) #(2 * FRAME_TB) uart_data_tb = 1;
	end
end

// fb
initial begin
	#1050;
	while (1'b1) begin
		#1250 fb_tb = ~fb_tb;
	end
end

initial begin
	#1050;
	while (1'b1) begin
		#(12 * 1250) fb_mask = ~fb_mask;
	end
end

// creating VCD file for signal analysis
initial begin
	$dumpfile("out.vcd");
	$dumpvars(0, test_entry);
end

// displaying meaning signals
initial $monitor(
		$stime,,
		clk_tb,,
		uart_clk_tb,,
		uart_data_tb,,
		sh_0,,
		sh_1,,
		sh_2,,
		sh_3,,
		sh_4,,
		out_tb,,
		//storage_tb,,
		//state_tb

		gen_out_tb,,

		fb_in_tb,,
		fb_out_tb,,

		sel_out_tb,,

		int_out_tb,,
	);

endmodule

out.vcd
$date
	Sun Nov 08 22:57:56 2020
$end
$version
	Icarus Verilog
$end
$timescale
	1ns
$end
$scope module test_entry $end
$var wire 1 ! fb_in_tb $end
$var wire 1 " out_tb $end
$var wire 8 # sh_0 [7:0] $end
$var wire 8 $ sh_1 [7:0] $end
$var wire 8 % sh_2 [7:0] $end
$var wire 8 & sh_3 [7:0] $end
$var wire 8 ' sh_4 [7:0] $end
$var wire 1 ( sel_out_tb $end
$var wire 1 ) int_out_tb $end
$var wire 1 * gen_out_tb $end
$var wire 1 + fb_out_tb $end
$var reg 1 , clk_tb $end
$var reg 1 - fb_mask $end
$var reg 1 . fb_tb $end
$var reg 1 / uart_clk_tb $end
$var reg 1 0 uart_data_tb $end
$scope module entry_inst $end
$var wire 1 , clk $end
$var wire 1 ! fb_in $end
$var wire 1 0 uart_data $end
$var wire 1 ( sel_out $end
$var wire 1 ) int_out $end
$var wire 1 * gen_out $end
$var wire 1 + fb_out $end
$scope module i1 $end
$var wire 1 , clk $end
$var wire 1 ) out $end
$var wire 1 1 int_wire $end
$var wire 1 2 gen_edge_p $end
$var wire 1 3 gen_del $end
$var wire 1 ( gen $end
$var reg 1 4 ff $end
$scope module gen_d $end
$var wire 1 , clk $end
$var wire 1 ( data_raw $end
$var reg 1 3 data $end
$var reg 1 5 internal $end
$upscope $end
$scope module gen_p $end
$var wire 1 , clk $end
$var wire 1 6 out $end
$var wire 1 7 out_n $end
$var wire 1 2 out_p $end
$var wire 1 ( sgn $end
$var reg 1 8 sgn_pre $end
$upscope $end
$scope module i $end
$var wire 1 , clk $end
$var wire 8 9 freq_par [7:0] $end
$var wire 8 : pw_par [7:0] $end
$var wire 1 1 out $end
$var reg 14 ; cnt [13:0] $end
$upscope $end
$upscope $end
$scope module p1 $end
$var wire 1 , clk $end
$var wire 1 ! sgn $end
$var wire 8 < shift [7:0] $end
$var reg 8 = cnt [7:0] $end
$var reg 1 + sgn_pre $end
$upscope $end
$scope module rg1 $end
$var wire 1 , clk $end
$var wire 8 > inp [7:0] $end
$var reg 9 ? cnt [8:0] $end
$var reg 8 @ gen_param [7:0] $end
$var reg 1 * out $end
$upscope $end
$scope module s1 $end
$var wire 1 , clk $end
$var wire 1 A cond_0 $end
$var wire 1 B cond_1 $end
$var wire 1 + fb $end
$var wire 1 * gen $end
$var wire 1 ( out $end
$var wire 1 C gen_edge_n $end
$var wire 1 D fb_edge_n $end
$var reg 3 E per_to_sw_cnt [2:0] $end
$var reg 1 F state $end
$var reg 9 G timeout_cnt [8:0] $end
$scope module edge_det_fb $end
$var wire 1 , clk $end
$var wire 1 H out $end
$var wire 1 D out_n $end
$var wire 1 I out_p $end
$var wire 1 + sgn $end
$var reg 1 J sgn_pre $end
$upscope $end
$scope module edge_det_gen $end
$var wire 1 , clk $end
$var wire 1 K out $end
$var wire 1 C out_n $end
$var wire 1 L out_p $end
$var wire 1 * sgn $end
$var reg 1 M sgn_pre $end
$upscope $end
$upscope $end
$upscope $end
$scope begin $ivl_for_loop1 $end
$var integer 32 N i [31:0] $end
$upscope $end
$upscope $end
$enddefinitions $end
#0
$dumpvars
b1000101 N
0M
0L
0K
0J
0I
0H
b110001111 G
0F
b100 E
0D
0C
0B
0A
b0 @
b0 ?
b0 >
b11110 =
b11110 <
b0 ;
b1101 :
b100 9
08
07
06
05
04
03
02
11
10
0/
0.
1-
0,
0+
0*
0)
0(
bz '
bz &
bz %
bz $
bz #
z"
0!
$end
#5
16
12
1(
1L
1K
1*
b1111100 ?
01
b100111000011 ;
1,
#10
0,
#15
02
0L
06
0K
14
15
18
b100111000010 ;
1M
b1111011 ?
1,
#20
0,
#25
1)
b1111010 ?
b100111000001 ;
13
1,
#30
0,
#35
b100111000000 ;
b1111001 ?
1,
#40
0,
#45
b1111000 ?
b100110111111 ;
1,
#50
0,
#55
b100110111110 ;
b1110111 ?
1,
#60
0,
#65
b1110110 ?
b100110111101 ;
1,
#70
0,
#75
b100110111100 ;
b1110101 ?
1,
#80
0,
#85
b1110100 ?
b100110111011 ;
1,
#90
0,
#95
b100110111010 ;
b1110011 ?
1,
#100
0,
#105
b1110010 ?
b100110111001 ;
1,
#110
0,
#115
b100110111000 ;
b1110001 ?
1,
#120
0,
#125
b1110000 ?
b100110110111 ;
1,
#130
0,
#135
b100110110110 ;
b1101111 ?
1,
#140
0,
#145
b1101110 ?
b100110110101 ;
1,
#150
0,
#155
b100110110100 ;
b1101101 ?
1,
#160
0,
#165
b1101100 ?
b100110110011 ;
1,
#170
0,
#175
b100110110010 ;
b1101011 ?
1,
#180
0,
#185
b1101010 ?
b100110110001 ;
1,
#190
0,
#195
b100110110000 ;
b1101001 ?
1,
#200
0,
#205
b1101000 ?
b100110101111 ;
1,
#210
0,
#215
b100110101110 ;
b1100111 ?
1,
#220
0,
#225
b1100110 ?
b100110101101 ;
1,
#230
0,
#235
b100110101100 ;
b1100101 ?
1,
#240
0,
#245
b1100100 ?
b100110101011 ;
1,
#250
0,
#255
b100110101010 ;
b1100011 ?
1,
#260
0,
#265
b1100010 ?
b100110101001 ;
1,
#270
0,
#275
b100110101000 ;
b1100001 ?
1,
#280
0,
#285
b1100000 ?
b100110100111 ;
1,
#290
0,
#295
b100110100110 ;
b1011111 ?
1,
#300
0,
#305
b1011110 ?
b100110100101 ;
1,
#310
0,
#315
b100110100100 ;
b1011101 ?
1,
#320
0,
#325
b1011100 ?
b100110100011 ;
1,
#330
0,
#335
b100110100010 ;
b1011011 ?
1,
#340
0,
#345
b1011010 ?
b100110100001 ;
1,
#350
0,
#355
b100110100000 ;
b1011001 ?
1,
#360
0,
#365
b1011000 ?
b100110011111 ;
1,
#370
0,
#375
b100110011110 ;
b1010111 ?
1,
#380
0,
#385
b1010110 ?
b100110011101 ;
1,
#390
0,
#395
b100110011100 ;
b1010101 ?
1,
#400
0,
#405
b1010100 ?
b100110011011 ;
1,
#410
0,
#415
b100110011010 ;
b1010011 ?
1,
#420
0,
#425
b1010010 ?
b100110011001 ;
1,
#430
0,
#435
b100110011000 ;
b1010001 ?
1,
#440
0,
#445
b1010000 ?
b100110010111 ;
1,
#450
0,
#455
b100110010110 ;
b1001111 ?
1,
#460
0,
#465
b1001110 ?
b100110010101 ;
1,
#470
0,
#475
b100110010100 ;
b1001101 ?
1,
#480
0,
#485
b1001100 ?
b100110010011 ;
1,
#490
0,
#495
b100110010010 ;
b1001011 ?
1,
#500
0,
#505
b1001010 ?
b100110010001 ;
1,
#510
0,
#515
b100110010000 ;
b1001001 ?
1,
#520
0,
#521
1/
#525
b1001000 ?
b100110001111 ;
1,
#530
0,
#535
b100110001110 ;
b1000111 ?
1,
#540
0,
#545
b1000110 ?
b100110001101 ;
1,
#550
0,
#555
b100110001100 ;
b1000101 ?
1,
#560
0,
#565
b1000100 ?
b100110001011 ;
1,
#570
0,
#575
b100110001010 ;
b1000011 ?
1,
#580
0,
#585
b1000010 ?
b100110001001 ;
1,
#590
0,
#595
b100110001000 ;
b1000001 ?
1,
#600
0,
#605
b1000000 ?
b100110000111 ;
1,
#610
0,
#615
b100110000110 ;
b111111 ?
1,
#620
0,
#625
b111110 ?
b100110000101 ;
1,
#630
0,
#635
b100110000100 ;
b111101 ?
1,
#640
0,
#645
b111100 ?
b100110000011 ;
1,
#650
0,
#655
b100110000010 ;
b111011 ?
1,
#660
0,
#665
b111010 ?
b100110000001 ;
1,
#670
0,
#675
b100110000000 ;
b111001 ?
1,
#680
0,
#685
b111000 ?
b100101111111 ;
1,
#690
0,
#695
b100101111110 ;
b110111 ?
1,
#700
0,
#705
b110110 ?
b100101111101 ;
1,
#710
0,
#715
b100101111100 ;
b110101 ?
1,
#720
0,
#725
b110100 ?
b100101111011 ;
1,
#730
0,
#735
b100101111010 ;
b110011 ?
1,
#740
0,
#745
b110010 ?
b100101111001 ;
1,
#750
0,
#755
b100101111000 ;
b110001 ?
1,
#760
0,
#765
b110000 ?
b100101110111 ;
1,
#770
0,
#775
b100101110110 ;
b101111 ?
1,
#780
0,
#785
b101110 ?
b100101110101 ;
1,
#790
0,
#795
b100101110100 ;
b101101 ?
1,
#800
0,
#805
b101100 ?
b100101110011 ;
1,
#810
0,
#815
b100101110010 ;
b101011 ?
1,
#820
0,
#825
b101010 ?
b100101110001 ;
1,
#830
0,
#835
b100101110000 ;
b101001 ?
1,
#840
0,
#845
b101000 ?
b100101101111 ;
1,
#850
0,
#855
b100101101110 ;
b100111 ?
1,
#860
0,
#865
b100110 ?
b100101101101 ;
1,
#870
0,
#875
b100101101100 ;
b100101 ?
1,
#880
0,
#885
b100100 ?
b100101101011 ;
1,
#890
0,
#895
b100101101010 ;
b100011 ?
1,
#900
0,
#905
b100010 ?
b100101101001 ;
1,
#910
0,
#915
b100101101000 ;
b100001 ?
1,
#920
0,
#925
b100000 ?
b100101100111 ;
1,
#930
0,
#935
b100101100110 ;
b11111 ?
1,
#940
0,
#945
b11110 ?
b100101100101 ;
1,
#950
0,
#955
b100101100100 ;
b11101 ?
1,
#960
0,
#965
b11100 ?
b100101100011 ;
1,
#970
0,
#975
b100101100010 ;
b11011 ?
1,
#980
0,
#985
b11010 ?
b100101100001 ;
1,
#990
0,
#995
b100101100000 ;
b11001 ?
1,
#1000
0,
#1005
b11000 ?
b100101011111 ;
1,
#1010
0,
#1015
b100101011110 ;
b10111 ?
1,
#1020
0,
#1025
b10110 ?
b100101011101 ;
1,
#1030
0,
#1035
b100101011100 ;
b10101 ?
1,
#1040
0,
#1042
0/
b1000100 N
00
#1045
b10100 ?
b100101011011 ;
1,
#1050
0,
#1055
b100101011010 ;
b10011 ?
1,
#1060
0,
#1065
b10010 ?
b100101011001 ;
1,
#1070
0,
#1075
b100101011000 ;
b10001 ?
1,
#1080
0,
#1085
b10000 ?
b100101010111 ;
1,
#1090
0,
#1095
b100101010110 ;
b1111 ?
1,
#1100
0,
#1105
b1110 ?
b100101010101 ;
1,
#1110
0,
#1115
b100101010100 ;
b1101 ?
1,
#1120
0,
#1125
b1100 ?
b100101010011 ;
1,
#1130
0,
#1135
b100101010010 ;
b1011 ?
1,
